{"Groudon-Primal": {"species": "Groudon-Primal", "abilities": [["Desolate Land", 100.0]], "items": [["Red Orb", 100.0]], "spreads": [{"nature": "Adamant", "evs": {"hp": 108, "atk": 148, "def": 0, "spa": 0, "spd": 252, "spe": 0}, "usage": 37.052}, {"nature": "Adamant", "evs": {"hp": 252, "atk": 252, "def": 4, "spa": 0, "spd": 0, "spe": 0}, "usage": 16.887}, {"nature": "Jolly", "evs": {"hp": 4, "atk": 252, "def": 0, "spa": 0, "spd": 0, "spe": 252}, "usage": 12.002}, {"nature": "Quiet", "evs": {"hp": 188, "atk": 44, "def": 0, "spa": 156, "spd": 68, "spe": 52}, "usage": 8.696}, {"nature": "Adamant", "evs": {"hp": 252, "atk": 252, "def": 0, "spa": 0, "spd": 4, "spe": 0}, "usage": 6.303}, {"nature": "Timid", "evs": {"hp": 4, "atk": 0, "def": 0, "spa": 252, "spd": 0, "spe": 252}, "usage": 5.45}], "moves": [["Protect", 100.0], ["Precipice Blades", 93.732], ["Fire Punch", 90.94], ["Rock Slide", 72.474], ["Eruption", 20.329], ["Earth Power", 9.06]], "teammates": [["Salamence-Mega", 2.498], ["Meowstic", 1.076], ["Weavile", 1.076], ["Vivillon", 1.076], ["Xerneas", 0.9], ["Thundurus", 0.751], ["Smeargle", 0.727], ["Talonflame", 0.615]], "checks": [], "metadata": {"raw": 163.0, "weight": 0.173339138981, "ceiling": 74.0}}, "Salamence-Mega": {"species": "Salamence-Mega", "abilities": [["Aerilate", 100.0]], "items": [["Salamencite", 100.0]], "spreads": [{"nature": "Naive", "evs": {"hp": 0, "atk": 4, "def": 0, "spa": 252, "spd": 0, "spe": 252}, "usage": 45.495}, {"nature": "Hasty", "evs": {"hp": 0, "atk": 204, "def": 0, "spa": 52, "spd": 0, "spe": 252}, "usage": 22.645}, {"nature": "Naive", "evs": {"hp": 0, "atk": 20, "def": 0, "spa": 236, "spd": 0, "spe": 252}, "usage": 13.811}, {"nature": "Hasty", "evs": {"hp": 20, "atk": 108, "def": 20, "spa": 108, "spd": 0, "spe": 252}, "usage": 7.95}, {"nature": "Hasty", "evs": {"hp": 0, "atk": 4, "def": 0, "spa": 252, "spd": 0, "spe": 252}, "usage": 6.271}], "moves": [["Hyper Voice", 100.0], ["Double-Edge", 99.059], ["Protect", 89.929], ["Tailwind", 66.757], ["Draco Meteor", 34.184]], "teammates": [["Xerneas", 6.385], ["Meowstic", 5.489], ["Weavile", 5.489], ["Vivillon", 5.489], ["Groudon-Primal", 3.516], ["Gengar", 2.292], ["Smeargle", 2.252], ["Talonflame", 1.08], ["Cresselia", 0.561]], "checks": [], "metadata": {"raw": 120.0, "weight": 0.204617521208, "ceiling": 74.0}}, "Xerneas": {"species": "Xerneas", "abilities": [["Fairy Aura", 100.0]], "items": [["Power Herb", 100.0]], "spreads": [{"nature": "Modest", "evs": {"hp": 28, "atk": 0, "def": 204, "spa": 252, "spd": 12, "spe": 12}, "usage": 52.597}, {"nature": "Timid", "evs": {"hp": 44, "atk": 0, "def": 0, "spa": 212, "spd": 0, "spe": 252}, "usage": 17.037}, {"nature": "Modest", "evs": {"hp": 76, "atk": 0, "def": 188, "spa": 4, "spd": 12, "spe": 228}, "usage": 9.808}, {"nature": "Modest", "evs": {"hp": 220, "atk": 0, "def": 108, "spa": 84, "spd": 4, "spe": 92}, "usage": 7.736}, {"nature": "Modest", "evs": {"hp": 244, "atk": 0, "def": 140, "spa": 12, "spd": 36, "spe": 76}, "usage": 3.631}, {"nature": "Modest", "evs": {"hp": 156, "atk": 0, "def": 76, "spa": 252, "spd": 4, "spe": 20}, "usage": 3.527}], "moves": [["Protect", 100.0], ["Geomancy", 100.0], ["Moonblast", 100.0], ["Dazzling Gleam", 100.0]], "teammates": [["Meowstic", 13.363], ["Weavile", 13.363], ["Vivillon", 13.363], ["Smeargle", 11.106], ["Salamence-Mega", 9.425], ["Talonflame", 7.636], ["Groudon-Primal", 3.701], ["Kangaskhan-Mega", 1.708], ["Infernape", 0.535]], "checks": [], "metadata": {"raw": 109.0, "weight": 0.182604286351, "ceiling": 74.0}}, "Kyogre-Primal": {"species": "Kyogre-Primal", "abilities": [["Primordial Sea", 100.0]], "items": [["Blue Orb", 100.0]], "spreads": [{"nature": "Modest", "evs": {"hp": 108, "atk": 0, "def": 124, "spa": 36, "spd": 4, "spe": 236}, "usage": 39.343}, {"nature": "Modest", "evs": {"hp": 204, "atk": 0, "def": 204, "spa": 44, "spd": 4, "spe": 52}, "usage": 31.293}, {"nature": "Modest", "evs": {"hp": 0, "atk": 0, "def": 252, "spa": 4, "spd": 0, "spe": 252}, "usage": 16.651}, {"nature": "Modest", "evs": {"hp": 252, "atk": 0, "def": 60, "spa": 196, "spd": 0, "spe": 0}, "usage": 3.529}, {"nature": "Modest", "evs": {"hp": 92, "atk": 0, "def": 0, "spa": 252, "spd": 0, "spe": 164}, "usage": 3.038}, {"nature": "Modest", "evs": {"hp": 236, "atk": 0, "def": 212, "spa": 60, "spd": 0, "spe": 0}, "usage": 2.556}], "moves": [["Protect", 100.0], ["Water Spout", 100.0], ["Ice Beam", 98.761], ["Origin Pulse", 91.564]], "teammates": [["Rayquaza-Mega", 11.115], ["Gengar-Mega", 10.726], ["Bronzong", 9.719], ["Hitmontop", 9.005], ["Raichu", 8.239], ["Gengar", 6.736], ["Thundurus", 6.434], ["Zapdos", 4.006], ["Porygon2", 2.9], ["Ferrothorn", 1.771], ["Mawile-Mega", 1.284], ["Galvantula", 1.105]], "checks": [], "metadata": {"raw": 157.0, "weight": 0.118852020185, "ceiling": 72.0}}, "Bronzong": {"species": "Bronzong", "abilities": [["Levitate", 80.536], ["Heatproof", 19.464]], "items": [["Lum Berry", 93.223], ["Mental Herb", 6.777]], "spreads": [{"nature": "Sassy", "evs": {"hp": 252, "atk": 0, "def": 68, "spa": 0, "spd": 188, "spe": 0}, "usage": 50.638}, {"nature": "Sassy", "evs": {"hp": 244, "atk": 76, "def": 0, "spa": 0, "spd": 188, "spe": 0}, "usage": 31.01}, {"nature": "Sassy", "evs": {"hp": 244, "atk": 0, "def": 148, "spa": 0, "spd": 116, "spe": 0}, "usage": 11.575}, {"nature": "Relaxed", "evs": {"hp": 252, "atk": 0, "def": 124, "spa": 0, "spd": 132, "spe": 0}, "usage": 4.563}], "moves": [["Trick Room", 100.0], ["Gyro Ball", 100.0], ["Skill Swap", 80.536], ["Gravity", 62.049], ["Safeguard", 37.951]], "teammates": [["Kyogre-Primal", 19.271], ["Hitmontop", 14.93], ["Raichu", 13.718], ["Thundurus", 12.365], ["Gengar-Mega", 11.868], ["Gengar", 10.675], ["Rayquaza-Mega", 8.623]], "checks": [], "metadata": {"raw": 94.0, "weight": 0.163684020379, "ceiling": 72.0}}, "Kangaskhan-Mega": {"species": "Kangaskhan-Mega", "abilities": [["Parental Bond", 100.0]], "items": [["Kangaskhanite", 100.0]], "spreads": [{"nature": "Jolly", "evs": {"hp": 4, "atk": 228, "def": 84, "spa": 0, "spd": 4, "spe": 188}, "usage": 23.092}, {"nature": "Brave", "evs": {"hp": 252, "atk": 252, "def": 0, "spa": 0, "spd": 4, "spe": 0}, "usage": 21.158}, {"nature": "Jolly", "evs": {"hp": 0, "atk": 252, "def": 0, "spa": 0, "spd": 4, "spe": 252}, "usage": 17.5}, {"nature": "Jolly", "evs": {"hp": 4, "atk": 244, "def": 4, "spa": 0, "spd": 4, "spe": 252}, "usage": 15.265}, {"nature": "Jolly", "evs": {"hp": 12, "atk": 164, "def": 76, "spa": 0, "spd": 4, "spe": 252}, "usage": 13.293}, {"nature": "Jolly", "evs": {"hp": 36, "atk": 124, "def": 92, "spa": 0, "spd": 4, "spe": 252}, "usage": 3.438}], "moves": [["Fake Out", 100.0], ["Double-Edge", 78.005], ["Sucker Punch", 77.268], ["Power-Up Punch", 39.729], ["Low Kick", 35.22], ["Return", 21.995], ["Crunch", 21.158], ["Hammer Arm", 21.158]], "teammates": [["Smeargle", 24.302], ["Talonflame", 16.079], ["Porygon2", 5.058], ["Ferrothorn", 3.928], ["Zapdos", 3.125], ["Amoonguss", 0.914]], "checks": [], "metadata": {"raw": 136.0, "weight": 0.107980022636, "ceiling": 72.0}}, "Vivillon": {"species": "Vivillon", "abilities": [["Friend Guard", 100.0], ["Shield Dust", 0.0]], "items": [["Coba Berry", 100.0]], "spreads": [{"nature": "Bold", "evs": {"hp": 252, "atk": 0, "def": 132, "spa": 4, "spd": 116, "spe": 4}, "usage": 100.0}], "moves": [["Struggle Bug", 100.0], ["Powder", 100.0], ["Rage Powder", 100.0], ["Sleep Powder", 100.0]], "teammates": [["Meowstic", 50.831], ["Weavile", 50.831], ["Xerneas", 24.686], ["Salamence-Mega", 13.536], ["Groudon-Primal", 4.306]], "checks": [], "metadata": {"raw": 18.0, "weight": 0.58159724945, "ceiling": 74.0}}, "Meowstic": {"species": "Meowstic", "abilities": [["Prankster", 100.0], ["Keen Eye", 0.0]], "items": [["Mental Herb", 100.0]], "spreads": [{"nature": "Impish", "evs": {"hp": 252, "atk": 0, "def": 108, "spa": 0, "spd": 148, "spe": 0}, "usage": 100.0}], "moves": [["Trick Room", 100.0], ["Swagger", 100.0], ["Gravity", 100.0], ["Safeguard", 100.0]], "teammates": [["Weavile", 50.831], ["Vivillon", 50.831], ["Xerneas", 24.686], ["Salamence-Mega", 13.536], ["Groudon-Primal", 4.306]], "checks": [], "metadata": {"raw": 21.0, "weight": 0.4985119281, "ceiling": 74.0}}, "Weavile": {"species": "Weavile", "abilities": [["Pressure", 100.0], ["Pickpocket", 0.0]], "items": [["Life Orb", 100.0]], "spreads": [{"nature": "Jolly", "evs": {"hp": 4, "atk": 252, "def": 0, "spa": 0, "spd": 0, "spe": 252}, "usage": 100.0}], "moves": [["Icicle Crash", 100.0], ["Foul Play", 100.0], ["Feint", 100.0], ["Fake Out", 100.0]], "teammates": [["Vivillon", 50.831], ["Meowstic", 50.831], ["Xerneas", 24.686], ["Salamence-Mega", 13.536], ["Groudon-Primal", 4.306]], "checks": [], "metadata": {"raw": 27.0, "weight": 0.387731499634, "ceiling": 74.0}}, "Smeargle": {"species": "Smeargle", "abilities": [["Moody", 99.273], ["Own Tempo", 0.727]], "items": [["Focus Sash", 58.912], ["Chesto Berry", 22.97], ["Mental Herb", 18.118]], "spreads": [{"nature": "Jolly", "evs": {"hp": 0, "atk": 0, "def": 252, "spa": 0, "spd": 0, "spe": 252}, "usage": 39.903}, {"nature": "Calm", "evs": {"hp": 252, "atk": 0, "def": 68, "spa": 0, "spd": 188, "spe": 0}, "usage": 22.97}, {"nature": "Relaxed", "evs": {"hp": 252, "atk": 0, "def": 236, "spa": 0, "spd": 20, "spe": 0}, "usage": 18.118}, {"nature": "Bold", "evs": {"hp": 252, "atk": 0, "def": 252, "spa": 0, "spd": 4, "spe": 0}, "usage": 8.261}, {"nature": "Timid", "evs": {"hp": 252, "atk": 0, "def": 4, "spa": 0, "spd": 0, "spe": 252}, "usage": 5.941}], "moves": [["Dark Void", 100.0], ["Fake Out", 63.963], ["Spiky Shield", 49.924], ["Follow Me", 49.924], ["King's Shield", 41.088], ["Wide Guard", 34.548], ["Crafty Shield", 31.231], ["Transform", 26.379]], "teammates": [["Kangaskhan-Mega", 49.675], ["Talonflame", 39.521], ["Xerneas", 29.714], ["Salamence-Mega", 12.622], ["Groudon-Primal", 10.095], ["Serperior", 0.541], ["Greninja", 0.517], ["Pidgeot-Mega", 0.517], ["Landorus-Therian", 0.517], ["Doublade", 0.517], ["Arcanine", 0.517]], "checks": [], "metadata": {"raw": 82.0, "weight": 0.103637486208, "ceiling": 71.0}}, "Rayquaza-Mega": {"species": "Rayquaza-Mega", "abilities": [["Delta Stream", 100.0]], "items": [["Focus Sash", 92.934], ["Life Orb", 7.066]], "spreads": [{"nature": "Jolly", "evs": {"hp": 4, "atk": 252, "def": 0, "spa": 0, "spd": 0, "spe": 252}, "usage": 57.755}, {"nature": "Hasty", "evs": {"hp": 4, "atk": 252, "def": 0, "spa": 0, "spd": 0, "spe": 252}, "usage": 35.038}, {"nature": "Jolly", "evs": {"hp": 0, "atk": 252, "def": 4, "spa": 0, "spd": 0, "spe": 252}, "usage": 7.066}], "moves": [["Extreme Speed", 100.0], ["Dragon Ascent", 100.0], ["Protect", 99.859], ["Swords Dance", 57.755], ["Draco Meteor", 30.376]], "teammates": [["Raichu", 32.703], ["Hitmontop", 29.421], ["Gengar-Mega", 27.614], ["Kyogre-Primal", 18.745], ["Ferrothorn", 11.58], ["Porygon2", 9.471], ["Zapdos", 7.538], ["Bronzong", 5.536], ["Infernape", 2.11]], "checks": [], "metadata": {"raw": 96.0, "weight": 0.106549608714, "ceiling": 71.0}}, "Thundurus": {"species": "Thundurus", "abilities": [["Prankster", 100.0]], "items": [["Sitrus Berry", 97.319]], "spreads": [{"nature": "Calm", "evs": {"hp": 244, "atk": 0, "def": 108, "spa": 64, "spd": 72, "spe": 20}, "usage": 55.339}, {"nature": "Modest", "evs": {"hp": 252, "atk": 0, "def": 112, "spa": 68, "spd": 4, "spe": 68}, "usage": 20.656}, {"nature": "Modest", "evs": {"hp": 252, "atk": 0, "def": 36, "spa": 148, "spd": 4, "spe": 68}, "usage": 9.15}, {"nature": "Hardy", "evs": {"hp": 0, "atk": 0, "def": 0, "spa": 0, "spd": 0, "spe": 0}, "usage": 8.223}, {"nature": "Calm", "evs": {"hp": 220, "atk": 0, "def": 44, "spa": 4, "spd": 164, "spe": 76}, "usage": 3.951}], "moves": [["Taunt", 100.0], ["Thunderbolt", 97.319], ["Thunder Wave", 97.319], ["Protect", 70.194], ["Hidden Power Ice", 20.656]], "teammates": [["Gengar", 28.291], ["Bronzong", 15.787], ["Kyogre-Primal", 13.793], ["Amoonguss", 11.858], ["Cresselia", 6.92], ["Yveltal", 5.071]], "checks": [], "metadata": {"raw": 55.0, "weight": 0.156765548524, "ceiling": 72.0}}, "Gengar-Mega": {"species": "Gengar-Mega", "abilities": [["Shadow Tag", 100.0]], "items": [["Gengarite", 100.0]], "spreads": [{"nature": "Timid", "evs": {"hp": 92, "atk": 0, "def": 20, "spa": 172, "spd": 4, "spe": 220}, "usage": 78.084}, {"nature": "Timid", "evs": {"hp": 12, "atk": 0, "def": 96, "spa": 180, "spd": 0, "spe": 220}, "usage": 8.806}, {"nature": "Timid", "evs": {"hp": 164, "atk": 0, "def": 4, "spa": 140, "spd": 12, "spe": 188}, "usage": 6.378}, {"nature": "Timid", "evs": {"hp": 0, "atk": 0, "def": 0, "spa": 252, "spd": 4, "spe": 252}, "usage": 5.866}], "moves": [["Sludge Bomb", 99.134], ["Protect", 99.134], ["Taunt", 86.89], ["Will-O-Wisp", 84.816], ["Hidden Power Ice", 8.806], ["Skill Swap", 6.378]], "teammates": [["Hitmontop", 48.717], ["Raichu", 46.743], ["Rayquaza-Mega", 41.648], ["Kyogre-Primal", 32.304], ["Bronzong", 22.815], ["Mawile-Mega", 6.561], ["Crobat", 5.431], ["Whimsicott", 1.502], ["Serperior", 0.645]], "checks": [], "metadata": {"raw": 65.0, "weight": 0.115046751413, "ceiling": 68.0}}, "Hitmontop": {"species": "Hitmontop", "abilities": [["Intimidate", 100.0]], "items": [["Eject Button", 94.853], ["Black Belt", 5.147]], "spreads": [{"nature": "Adamant", "evs": {"hp": 252, "atk": 132, "def": 76, "spa": 0, "spd": 44, "spe": 4}, "usage": 51.708}, {"nature": "Adamant", "evs": {"hp": 252, "atk": 132, "def": 4, "spa": 0, "spd": 108, "spe": 12}, "usage": 36.517}, {"nature": "Careful", "evs": {"hp": 156, "atk": 100, "def": 0, "spa": 0, "spd": 252, "spe": 0}, "usage": 6.628}, {"nature": "Adamant", "evs": {"hp": 252, "atk": 84, "def": 172, "spa": 0, "spd": 0, "spe": 0}, "usage": 5.147}], "moves": [["Wide Guard", 100.0], ["Fake Out", 100.0], ["Close Combat", 100.0], ["Feint", 93.372]], "teammates": [["Gengar-Mega", 55.515], ["Raichu", 55.087], ["Rayquaza-Mega", 49.992], ["Bronzong", 34.075], ["Kyogre-Primal", 32.104], ["Whimsicott", 1.764]], "checks": [], "metadata": {"raw": 57.0, "weight": 0.116114652891, "ceiling": 68.0}}, "Raichu": {"species": "Raichu", "abilities": [["Lightning Rod", 100.0], ["Static", 0.0]], "items": [["Assault Vest", 94.035], ["Zap Plate", 5.965]], "spreads": [{"nature": "Timid", "evs": {"hp": 36, "atk": 0, "def": 204, "spa": 20, "spd": 68, "spe": 180}, "usage": 52.154}, {"nature": "Timid", "evs": {"hp": 36, "atk": 0, "def": 204, "spa": 20, "spd": 60, "spe": 188}, "usage": 36.832}, {"nature": "Jolly", "evs": {"hp": 0, "atk": 252, "def": 0, "spa": 0, "spd": 4, "spe": 252}, "usage": 11.014}], "moves": [["Nuzzle", 100.0], ["Fake Out", 100.0], ["Volt Switch", 88.986], ["Endeavor", 88.986], ["Volt Tackle", 11.014]], "teammates": [["Hitmontop", 55.672], ["Rayquaza-Mega", 55.668], ["Gengar-Mega", 53.864], ["Bronzong", 31.786], ["Kyogre-Primal", 30.453], ["Infernape", 3.92], ["Crobat", 1.675]], "checks": [], "metadata": {"raw": 48.0, "weight": 0.136706074859, "ceiling": 68.0}}, "Talonflame": {"species": "Talonflame", "abilities": [["Gale Wings", 100.0], ["Flame Body", 0.0]], "items": [["Choice Band", 62.385], ["Life Orb", 28.326], ["Lum Berry", 9.289]], "spreads": [{"nature": "Adamant", "evs": {"hp": 0, "atk": 252, "def": 0, "spa": 0, "spd": 4, "spe": 252}, "usage": 62.385}, {"nature": "Jolly", "evs": {"hp": 44, "atk": 188, "def": 4, "spa": 0, "spd": 60, "spe": 212}, "usage": 28.326}, {"nature": "Jolly", "evs": {"hp": 252, "atk": 108, "def": 76, "spa": 0, "spd": 20, "spe": 52}, "usage": 9.289}], "moves": [["Brave Bird", 100.0], ["Tailwind", 100.0], ["Flare Blitz", 76.318], ["Quick Guard", 62.385], ["Swords Dance", 28.326], ["Taunt", 23.682]], "teammates": [["Smeargle", 62.203], ["Kangaskhan-Mega", 51.836], ["Xerneas", 32.636], ["Groudon-Primal", 12.256], ["Salamence-Mega", 12.197]], "checks": [], "metadata": {"raw": 56.0, "weight": 0.0970667697019, "ceiling": 72.0}}, "Gengar": {"species": "Gengar", "abilities": [["Levitate", 100.0]], "items": [["Focus Sash", 100.0]], "spreads": [{"nature": "Timid", "evs": {"hp": 0, "atk": 0, "def": 0, "spa": 252, "spd": 4, "spe": 252}, "usage": 100.0}], "moves": [["Sludge Bomb", 100.0], ["Skill Swap", 100.0], ["Icy Wind", 100.0], ["Protect", 100.0]], "teammates": [["Thundurus", 52.705], ["Bronzong", 30.969], ["Kyogre-Primal", 29.636], ["Salamence-Mega", 6.901]], "checks": [], "metadata": {"raw": 24.0, "weight": 0.198806495829, "ceiling": 72.0}}, "Amoonguss": {"species": "Amoonguss", "abilities": [["Effect Spore", 85.474], ["Regenerator", 14.526]], "items": [["Focus Sash", 66.142], ["Chesto Berry", 14.526], ["Red Card", 10.344], ["Rocky Helmet", 8.988]], "spreads": [{"nature": "Relaxed", "evs": {"hp": 252, "atk": 0, "def": 252, "spa": 4, "spd": 0, "spe": 0}, "usage": 52.651}, {"nature": "Calm", "evs": {"hp": 252, "atk": 0, "def": 76, "spa": 0, "spd": 176, "spe": 0}, "usage": 14.526}, {"nature": "Relaxed", "evs": {"hp": 252, "atk": 0, "def": 252, "spa": 0, "spd": 4, "spe": 0}, "usage": 13.491}, {"nature": "Sassy", "evs": {"hp": 180, "atk": 0, "def": 92, "spa": 0, "spd": 236, "spe": 0}, "usage": 10.344}, {"nature": "Bold", "evs": {"hp": 4, "atk": 0, "def": 252, "spa": 130, "spd": 122, "spe": 0}, "usage": 8.988}], "moves": [["Spore", 100.0], ["Rage Powder", 100.0], ["Protect", 91.012], ["Grass Knot", 89.656]], "teammates": [["Thundurus", 21.175], ["Yveltal", 14.463], ["Cresselia", 11.645], ["Mawile-Mega", 11.246], ["Crobat", 10.117], ["Whimsicott", 2.575], ["Kangaskhan-Mega", 1.54]], "checks": [], "metadata": {"raw": 36.0, "weight": 0.135584771306, "ceiling": 72.0}}, "Zapdos": {"species": "Zapdos", "abilities": [["Pressure", 84.569], ["Static", 15.431]], "items": [["Sitrus Berry", 84.569], ["Rocky Helmet", 15.431]], "spreads": [{"nature": "Calm", "evs": {"hp": 244, "atk": 0, "def": 0, "spa": 68, "spd": 0, "spe": 196}, "usage": 84.569}, {"nature": "Modest", "evs": {"hp": 252, "atk": 0, "def": 108, "spa": 148, "spd": 0, "spe": 0}, "usage": 15.431}], "moves": [["Tailwind", 100.0], ["Heat Wave", 100.0], ["Thunder", 100.0], ["Roar", 84.569]], "teammates": [["Porygon2", 35.414], ["Ferrothorn", 34.284], ["Rayquaza-Mega", 17.879], ["Galvantula", 13.499], ["Swampert-Mega", 13.499], ["Ludicolo", 13.499], ["Parasect", 13.499], ["Kyogre-Primal", 13.145], ["Kangaskhan-Mega", 5.329]], "checks": [], "metadata": {"raw": 29.0, "weight": 0.126690629187, "ceiling": 68.0}}, "Ferrothorn": {"species": "Ferrothorn", "abilities": [["Iron Barbs", 100.0], ["Anticipation", 0.0]], "items": [["Leftovers", 81.129], ["Sitrus Berry", 18.871]], "spreads": [{"nature": "Brave", "evs": {"hp": 252, "atk": 252, "def": 0, "spa": 0, "spd": 4, "spe": 0}, "usage": 81.129}, {"nature": "Brave", "evs": {"hp": 252, "atk": 252, "def": 4, "spa": 0, "spd": 0, "spe": 0}, "usage": 18.871}], "moves": [["Protect", 100.0], ["Gyro Ball", 100.0], ["Seed Bomb", 81.129], ["Worry Seed", 81.129], ["Power Whip", 18.871]], "teammates": [["Porygon2", 33.767], ["Zapdos", 31.834], ["Rayquaza-Mega", 24.883], ["Infernape", 7.522], ["Crobat", 5.277], ["Kangaskhan-Mega", 3.682]], "checks": [], "metadata": {"raw": 47.0, "weight": 0.0814848284559, "ceiling": 71.0}}, "Porygon2": {"species": "Porygon2", "abilities": [["Download", 100.0], ["Trace", 0.0]], "items": [["Eviolite", 100.0]], "spreads": [{"nature": "Quiet", "evs": {"hp": 244, "atk": 0, "def": 16, "spa": 248, "spd": 0, "spe": 0}, "usage": 100.0}], "moves": [["Trick Room", 100.0], ["Hidden Power Water", 100.0], ["Tri Attack", 100.0], ["Ice Beam", 100.0]], "teammates": [["Ferrothorn", 41.672], ["Zapdos", 40.868], ["Rayquaza-Mega", 25.266], ["Kangaskhan-Mega", 12.716], ["Kyogre-Primal", 5.101]], "checks": [], "metadata": {"raw": 19.0, "weight": 0.163530145498, "ceiling": 68.0}}, "Crobat": {"species": "Crobat", "abilities": [["Inner Focus", 100.0], ["Infiltrator", 0.0]], "items": [["Lum Berry", 100.0]], "spreads": [{"nature": "Timid", "evs": {"hp": 20, "atk": 0, "def": 236, "spa": 0, "spd": 0, "spe": 252}, "usage": 100.0}], "moves": [["Tailwind", 100.0], ["Haze", 100.0], ["Super Fang", 100.0], ["Taunt", 52.324], ["Quick Guard", 47.676]], "teammates": [["Mawile-Mega", 45.431], ["Amoonguss", 36.393], ["Gengar-Mega", 28.315], ["Infernape", 22.858], ["Ferrothorn", 17.787], ["Raichu", 6.477], ["Kyogre-Primal", 4.904], ["Rayquaza-Mega", 1.382]], "checks": [], "metadata": {"raw": 16.0, "weight": 0.0863266835273, "ceiling": 65.0}}, "Yveltal": {"species": "Yveltal", "abilities": [["Dark Aura", 100.0]], "items": [["Life Orb", 63.817], ["Black Glasses", 36.183]], "spreads": [{"nature": "Jolly", "evs": {"hp": 148, "atk": 84, "def": 4, "spa": 0, "spd": 20, "spe": 252}, "usage": 58.478}, {"nature": "Adamant", "evs": {"hp": 4, "atk": 252, "def": 0, "spa": 0, "spd": 0, "spe": 252}, "usage": 36.183}, {"nature": "Timid", "evs": {"hp": 4, "atk": 0, "def": 0, "spa": 252, "spd": 0, "spe": 252}, "usage": 5.339}], "moves": [["Protect", 100.0], ["Knock Off", 94.661], ["Foul Play", 94.661], ["Sucker Punch", 94.661]], "teammates": [["Amoonguss", 59.63], ["Cresselia", 55.597], ["Thundurus", 38.776], ["Whimsicott", 11.921], ["Serperior", 5.118]], "checks": [], "metadata": {"raw": 25.0, "weight": 0.0484971889998, "ceiling": 72.0}}, "Cresselia": {"species": "Cresselia", "abilities": [["Levitate", 100.0]], "items": [["Leftovers", 75.414], ["Iapapa Berry", 24.586]], "spreads": [{"nature": "Calm", "evs": {"hp": 252, "atk": 0, "def": 116, "spa": 4, "spd": 116, "spe": 20}, "usage": 75.414}, {"nature": "Modest", "evs": {"hp": 252, "atk": 0, "def": 68, "spa": 120, "spd": 66, "spe": 0}, "usage": 24.586}], "moves": [["Trick Room", 100.0], ["Helping Hand", 100.0], ["Icy Wind", 75.414], ["Skill Swap", 75.414], ["Protect", 24.586], ["Psyshock", 24.586]], "teammates": [["Yveltal", 72.262], ["Thundurus", 70.178], ["Amoonguss", 64.131], ["Salamence-Mega", 24.375], ["Groudon-Primal", 15.144]], "checks": [], "metadata": {"raw": 34.0, "weight": 0.0276515062337, "ceiling": 72.0}}, "Mawile-Mega": {"species": "Mawile-Mega", "abilities": [["Huge Power", 100.0]], "items": [["Mawilite", 100.0]], "spreads": [{"nature": "Adamant", "evs": {"hp": 252, "atk": 188, "def": 0, "spa": 0, "spd": 0, "spe": 68}, "usage": 100.0}], "moves": [["Protect", 100.0], ["Play Rough", 100.0], ["Sucker Punch", 100.0], ["Iron Head", 100.0]], "teammates": [["Crobat", 96.625], ["Amoonguss", 88.717], ["Gengar-Mega", 80.639], ["Kyogre-Primal", 57.228], ["Groudon-Primal", 25.264]], "checks": [], "metadata": {"raw": 22.0, "weight": 0.0299323983395, "ceiling": 70.0}}, "Swampert-Mega": {"species": "Swampert-Mega", "abilities": [["Swift Swim", 100.0]], "items": [["Swampertite", 100.0]], "spreads": [{"nature": "Adamant", "evs": {"hp": 0, "atk": 252, "def": 0, "spa": 0, "spd": 4, "spe": 252}, "usage": 100.0}], "moves": [["Protect", 100.0], ["Waterfall", 100.0], ["Earthquake", 100.0], ["Superpower", 100.0]], "teammates": [["Galvantula", 98.067], ["Parasect", 98.067], ["Ludicolo", 98.067], ["Zapdos", 92.996], ["Kyogre-Primal", 57.228]], "checks": [], "metadata": {"raw": 9.0, "weight": 0.0629950535513, "ceiling": 60.0}}, "Parasect": {"species": "Parasect", "abilities": [["Dry Skin", 100.0]], "items": [["Leftovers", 100.0]], "spreads": [{"nature": "Calm", "evs": {"hp": 252, "atk": 0, "def": 4, "spa": 0, "spd": 252, "spe": 0}, "usage": 100.0}], "moves": [["Leech Seed", 100.0], ["Spore", 100.0], ["Wide Guard", 100.0], ["Rage Powder", 100.0]], "teammates": [["Galvantula", 98.067], ["Swampert-Mega", 98.067], ["Ludicolo", 98.067], ["Zapdos", 92.996], ["Kyogre-Primal", 57.228]], "checks": [], "metadata": {"raw": 7.0, "weight": 0.0809936402802, "ceiling": 60.0}}, "Galvantula": {"species": "Galvantula", "abilities": [["Compound Eyes", 100.0]], "items": [["Focus Sash", 100.0]], "spreads": [{"nature": "Timid", "evs": {"hp": 0, "atk": 0, "def": 0, "spa": 252, "spd": 4, "spe": 252}, "usage": 100.0}], "moves": [["Gastro Acid", 100.0], ["Sticky Web", 100.0], ["Thunder", 100.0], ["Bug Buzz", 100.0]], "teammates": [["Ludicolo", 98.067], ["Parasect", 98.067], ["Swampert-Mega", 98.067], ["Zapdos", 92.996], ["Kyogre-Primal", 57.228]], "checks": [], "metadata": {"raw": 8.0, "weight": 0.0708694352452, "ceiling": 60.0}}, "Ludicolo": {"species": "Ludicolo", "abilities": [["Swift Swim", 100.0]], "items": [["Assault Vest", 100.0]], "spreads": [{"nature": "Mild", "evs": {"hp": 0, "atk": 4, "def": 0, "spa": 252, "spd": 0, "spe": 252}, "usage": 100.0}], "moves": [["Scald", 100.0], ["Ice Beam", 100.0], ["Fake Out", 100.0], ["Giga Drain", 100.0]], "teammates": [["Galvantula", 98.067], ["Parasect", 98.067], ["Swampert-Mega", 98.067], ["Zapdos", 92.996], ["Kyogre-Primal", 57.228]], "checks": [], "metadata": {"raw": 7.0, "weight": 0.0809936402802, "ceiling": 60.0}}, "Infernape": {"species": "Infernape", "abilities": [["Blaze", 100.0]], "items": [["Focus Sash", 100.0]], "spreads": [{"nature": "Jolly", "evs": {"hp": 0, "atk": 252, "def": 0, "spa": 0, "spd": 4, "spe": 252}, "usage": 100.0}], "moves": [["Close Combat", 100.0], ["Fake Out", 100.0], ["Flare Blitz", 100.0], ["Encore", 100.0]], "teammates": [["Crobat", 42.47], ["Ferrothorn", 39.644], ["Raichu", 28.334], ["Rayquaza-Mega", 23.238]], "checks": [], "metadata": {"raw": 4.0, "weight": 0.180678543242, "ceiling": 64.0}}, "Whimsicott": {"species": "Whimsicott", "abilities": [["Prankster", 100.0], ["Infiltrator", 0.0], ["Chlorophyll", 0.0]], "items": [["Mental Herb", 52.088], ["Focus Sash", 47.912]], "spreads": [{"nature": "Timid", "evs": {"hp": 236, "atk": 0, "def": 0, "spa": 0, "spd": 220, "spe": 52}, "usage": 52.088}, {"nature": "Timid", "evs": {"hp": 156, "atk": 0, "def": 100, "spa": 0, "spd": 0, "spe": 252}, "usage": 47.912}], "moves": [["Tailwind", 100.0], ["Encore", 100.0], ["Endeavor", 52.088], ["Safeguard", 52.088], ["Fake Tears", 47.912], ["Moonblast", 47.912]], "teammates": [["Yveltal", 13.314], ["Amoonguss", 5.183]], "checks": [], "metadata": {"raw": 20.0, "weight": 0.0457808433103, "ceiling": 65.0}}, "Serperior": {"species": "Serperior", "abilities": [["Contrary", 100.0]], "items": [["Leftovers", 100.0]], "spreads": [{"nature": "Timid", "evs": {"hp": 56, "atk": 0, "def": 0, "spa": 200, "spd": 0, "spe": 252}, "usage": 100.0}], "moves": [["Leaf Storm", 100.0], ["Hidden Power Psychic", 100.0], ["Substitute", 100.0], ["Dragon Pulse", 100.0]], "teammates": [["Yveltal", 96.848], ["Gengar-Mega", 80.639], ["Smeargle", 75.211], ["Kangaskhan-Mega", 64.844], ["Groudon-Primal", 25.264]], "checks": [], "metadata": {"raw": 2.0, "weight": 0.032365895958, "ceiling": 53.0}}, "Pidgeot-Mega": {"species": "Pidgeot-Mega", "abilities": [["No Guard", 100.0]], "items": [["Pidgeotite", 100.0]], "spreads": [{"nature": "Modest", "evs": {"hp": 4, "atk": 0, "def": 0, "spa": 252, "spd": 0, "spe": 252}, "usage": 100.0}], "moves": [["Protect", 100.0], ["Tailwind", 100.0], ["Hurricane", 100.0], ["Twister", 100.0]], "teammates": [["Greninja", 99.789], ["Doublade", 99.789], ["Landorus-Therian", 99.789], ["Arcanine", 99.789], ["Smeargle", 75.211]], "checks": [], "metadata": {"raw": 8.0, "weight": 0.00772576332905, "ceiling": 61.0}}, "Landorus-Therian": {"species": "Landorus-Therian", "abilities": [["Intimidate", 100.0]], "items": [["Choice Band", 82.018], ["Sitrus Berry", 17.982]], "spreads": [{"nature": "Jolly", "evs": {"hp": 4, "atk": 252, "def": 0, "spa": 0, "spd": 0, "spe": 252}, "usage": 82.018}, {"nature": "Jolly", "evs": {"hp": 0, "atk": 0, "def": 124, "spa": 0, "spd": 130, "spe": 252}, "usage": 17.982}], "moves": [["Rock Slide", 100.0], ["U-turn", 82.018], ["Explosion", 82.018], ["Earthquake", 82.018], ["Protect", 17.982], ["Fissure", 17.982]], "teammates": [["Greninja", 17.771], ["Pidgeot-Mega", 17.771], ["Doublade", 17.771], ["Arcanine", 17.771]], "checks": [], "metadata": {"raw": 37.0, "weight": 0.00928951320482, "ceiling": 71.0}}, "Doublade": {"species": "Doublade", "abilities": [["No Guard", 100.0]], "items": [["Eviolite", 100.0]], "spreads": [{"nature": "Hardy", "evs": {"hp": 0, "atk": 0, "def": 0, "spa": 0, "spd": 0, "spe": 0}, "usage": 100.0}], "moves": [["Protect", 100.0], ["Destiny Bond", 100.0], ["Wide Guard", 100.0], ["Shadow Sneak", 100.0]], "teammates": [["Landorus-Therian", 99.789], ["Arcanine", 99.789], ["Greninja", 99.789], ["Pidgeot-Mega", 99.789], ["Smeargle", 75.211]], "checks": [], "metadata": {"raw": 7.0, "weight": 0.00882944380463, "ceiling": 61.0}}, "Arcanine": {"species": "Arcanine", "abilities": [["Intimidate", 100.0]], "items": [["Assault Vest", 100.0]], "spreads": [{"nature": "Adamant", "evs": {"hp": 180, "atk": 156, "def": 0, "spa": 0, "spd": 0, "spe": 172}, "usage": 100.0}], "moves": [["Extreme Speed", 100.0], ["Snarl", 100.0], ["Flare Blitz", 100.0], ["Bulldoze", 100.0]], "teammates": [["Doublade", 99.789], ["Greninja", 99.789], ["Pidgeot-Mega", 99.789], ["Landorus-Therian", 99.789], ["Smeargle", 75.211]], "checks": [], "metadata": {"raw": 13.0, "weight": 0.0047543158948, "ceiling": 61.0}}, "Greninja": {"species": "Greninja", "abilities": [["Protean", 100.0]], "items": [["Life Orb", 100.0]], "spreads": [{"nature": "Modest", "evs": {"hp": 4, "atk": 0, "def": 0, "spa": 252, "spd": 0, "spe": 252}, "usage": 100.0}], "moves": [["Scald", 100.0], ["Dark Pulse", 100.0], ["Ice Beam", 100.0], ["Toxic", 100.0]], "teammates": [["Doublade", 99.789], ["Pidgeot-Mega", 99.789], ["Landorus-Therian", 99.789], ["Arcanine", 99.789], ["Smeargle", 75.211]], "checks": [], "metadata": {"raw": 9.0, "weight": 0.00686734518138, "ceiling": 61.0}}, "Golduck": {"species": "Golduck", "abilities": [["Cloud Nine", 100.0]], "items": [["Sitrus Berry", 100.0]], "spreads": [{"nature": "Modest", "evs": {"hp": 156, "atk": 0, "def": 0, "spa": 236, "spd": 0, "spe": 116}, "usage": 100.0}], "moves": [["Surf", 100.0], ["Protect", 100.0], ["Encore", 100.0], ["Ice Beam", 100.0]], "teammates": [["Dialga", 48.939], ["Aromatisse", 48.939], ["Dugtrio", 48.939], ["Vespiquen", 48.939], ["Rayquaza-Mega", 26.357]], "checks": [], "metadata": {"raw": 9.0, "weight": 0.0016032177047, "ceiling": 47.0}}, "Aromatisse": {"species": "Aromatisse", "abilities": [["Aroma Veil", 100.0]], "items": [["Leftovers", 100.0]], "spreads": [{"nature": "Serious", "evs": {"hp": 188, "atk": 0, "def": 140, "spa": 80, "spd": 100, "spe": 0}, "usage": 100.0}], "moves": [["Heal Pulse", 100.0], ["Calm Mind", 100.0], ["Heal Bell", 100.0], ["Dazzling Gleam", 100.0]], "teammates": [["Dialga", 48.939], ["Golduck", 48.939], ["Vespiquen", 48.939], ["Dugtrio", 48.939], ["Rayquaza-Mega", 26.357]], "checks": [], "metadata": {"raw": 9.0, "weight": 0.0016032177047, "ceiling": 47.0}}, "Dugtrio": {"species": "Dugtrio", "abilities": [["Arena Trap", 100.0]], "items": [["King's Rock", 100.0]], "spreads": [{"nature": "Jolly", "evs": {"hp": 4, "atk": 252, "def": 0, "spa": 0, "spd": 0, "spe": 252}, "usage": 100.0}], "moves": [["Protect", 100.0], ["Sucker Punch", 100.0], ["Earthquake", 100.0], ["Rock Slide", 100.0]], "teammates": [["Dialga", 48.939], ["Golduck", 48.939], ["Aromatisse", 48.939], ["Vespiquen", 48.939], ["Rayquaza-Mega", 26.357]], "checks": [], "metadata": {"raw": 9.0, "weight": 0.0016032177047, "ceiling": 47.0}}, "Vespiquen": {"species": "Vespiquen", "abilities": [["Unnerve", 100.0]], "items": [["Rocky Helmet", 100.0]], "spreads": [{"nature": "Adamant", "evs": {"hp": 4, "atk": 0, "def": 252, "spa": 0, "spd": 252, "spe": 0}, "usage": 100.0}], "moves": [["Attack Order", 100.0], ["Defend Order", 100.0], ["Substitute", 100.0], ["Heal Order", 100.0]], "teammates": [["Dialga", 48.939], ["Golduck", 48.939], ["Aromatisse", 48.939], ["Dugtrio", 48.939], ["Rayquaza-Mega", 26.357]], "checks": [], "metadata": {"raw": 9.0, "weight": 0.0016032177047, "ceiling": 47.0}}, "Dialga": {"species": "Dialga", "abilities": [["Telepathy", 100.0], ["Pressure", 0.0]], "items": [["Adamant Orb", 100.0]], "spreads": [{"nature": "Modest", "evs": {"hp": 252, "atk": 0, "def": 4, "spa": 252, "spd": 0, "spe": 0}, "usage": 100.0}], "moves": [["Dragon Pulse", 100.0], ["Toxic", 100.0], ["Stealth Rock", 100.0], ["Flash Cannon", 100.0]], "teammates": [["Aromatisse", 48.939], ["Golduck", 48.939], ["Dugtrio", 48.939], ["Vespiquen", 48.939], ["Rayquaza-Mega", 26.357]], "checks": [], "metadata": {"raw": 21.0, "weight": 0.000687093302013, "ceiling": 66.0}}}