{"Landorus-Therian": {"species": "Landorus-Therian", "abilities": [["Intimidate", 100.0]], "items": [["Choice Scarf", 49.629], ["Assault Vest", 30.606], ["Focus Sash", 15.395]], "spreads": [{"nature": "Adamant", "evs": {"hp": 164, "atk": 172, "def": 4, "spa": 0, "spd": 76, "spe": 92}, "usage": 30.606}, {"nature": "Adamant", "evs": {"hp": 12, "atk": 148, "def": 92, "spa": 0, "spd": 4, "spe": 252}, "usage": 25.968}, {"nature": "Adamant", "evs": {"hp": 4, "atk": 252, "def": 0, "spa": 0, "spd": 0, "spe": 252}, "usage": 15.395}, {"nature": "Adamant", "evs": {"hp": 12, "atk": 220, "def": 92, "spa": 0, "spd": 4, "spe": 180}, "usage": 10.919}, {"nature": "Adamant", "evs": {"hp": 0, "atk": 252, "def": 0, "spa": 0, "spd": 4, "spe": 252}, "usage": 4.837}, {"nature": "Jolly", "evs": {"hp": 0, "atk": 252, "def": 68, "spa": 0, "spd": 0, "spe": 184}, "usage": 4.77}], "moves": [["Rock Slide", 100.0], ["Earthquake", 100.0], ["Superpower", 84.605], ["U-turn", 49.629], ["Knock Off", 46.001]], "teammates": [["Thundurus", 17.476], ["Amoonguss", 16.127], ["Cresselia", 13.838], ["Scrafty", 8.364], ["Charizard-Mega-Y", 6.279], ["Heatran", 6.156], ["Kangaskhan-Mega", 5.591], ["Thundurus-Therian", 4.355], ["Lucario-Mega", 4.355], ["Azumarill", 2.65], ["Togekiss", 1.941], ["Weavile", 1.368]], "checks": [], "metadata": {"raw": 42.0, "weight": 0.47955972034, "ceiling": 84.0}}, "Heatran": {"species": "Heatran", "abilities": [["Flash Fire", 100.0]], "items": [["Shuca Berry", 100.0]], "spreads": [{"nature": "Modest", "evs": {"hp": 244, "atk": 0, "def": 12, "spa": 252, "spd": 0, "spe": 0}, "usage": 33.403}, {"nature": "Modest", "evs": {"hp": 252, "atk": 0, "def": 0, "spa": 252, "spd": 0, "spe": 4}, "usage": 28.341}, {"nature": "Modest", "evs": {"hp": 44, "atk": 0, "def": 4, "spa": 252, "spd": 4, "spe": 204}, "usage": 17.056}, {"nature": "Modest", "evs": {"hp": 132, "atk": 0, "def": 20, "spa": 132, "spd": 12, "spe": 212}, "usage": 11.917}, {"nature": "Modest", "evs": {"hp": 88, "atk": 0, "def": 0, "spa": 184, "spd": 0, "spe": 236}, "usage": 4.769}], "moves": [["Protect", 100.0], ["Earth Power", 100.0], ["Heat Wave", 100.0], ["Substitute", 49.834], ["Hidden Power Ice", 33.11]], "teammates": [["Amoonguss", 26.81], ["Thundurus", 23.389], ["Kangaskhan-Mega", 13.901], ["Gardevoir-Mega", 11.872], ["Scrafty", 11.136], ["Landorus-Therian", 6.719], ["Crobat", 5.849], ["Rhyperior", 5.849], ["Ludicolo", 4.529], ["Azumarill", 3.648], ["Hitmontop", 3.601], ["Latios", 1.636]], "checks": [], "metadata": {"raw": 35.0, "weight": 0.527281958123, "ceiling": 77.0}}, "Thundurus": {"species": "Thundurus", "abilities": [["Prankster", 100.0]], "items": [["Sitrus Berry", 80.294], ["Safety Goggles", 19.706]], "spreads": [{"nature": "Modest", "evs": {"hp": 252, "atk": 0, "def": 160, "spa": 4, "spd": 68, "spe": 20}, "usage": 40.06}, {"nature": "Calm", "evs": {"hp": 252, "atk": 0, "def": 84, "spa": 0, "spd": 132, "spe": 40}, "usage": 33.99}, {"nature": "Calm", "evs": {"hp": 212, "atk": 0, "def": 212, "spa": 4, "spd": 44, "spe": 36}, "usage": 14.292}, {"nature": "Bold", "evs": {"hp": 252, "atk": 0, "def": 204, "spa": 4, "spd": 12, "spe": 36}, "usage": 6.244}, {"nature": "Timid", "evs": {"hp": 252, "atk": 0, "def": 0, "spa": 0, "spd": 252, "spe": 4}, "usage": 5.414}], "moves": [["Thunderbolt", 100.0], ["Thunder Wave", 93.756], ["Hidden Power Ice", 74.05], ["Taunt", 70.991], ["Swagger", 35.253], ["Protect", 25.95]], "teammates": [["Amoonguss", 42.39], ["Heatran", 28.05], ["Kangaskhan-Mega", 23.833], ["Landorus-Therian", 22.875], ["Scrafty", 12.016], ["Azumarill", 6.023], ["Cresselia", 4.762], ["Pinsir-Mega", 2.823], ["Porygon2", 2.448], ["Kingdra", 2.388], ["Politoed", 1.503]], "checks": [], "metadata": {"raw": 28.0, "weight": 0.549570324556, "ceiling": 80.0}}, "Amoonguss": {"species": "Amoonguss", "abilities": [["Regenerator", 100.0], ["Effect Spore", 0.0]], "items": [["Rocky Helmet", 100.0]], "spreads": [{"nature": "Relaxed", "evs": {"hp": 252, "atk": 0, "def": 172, "spa": 0, "spd": 84, "spe": 0}, "usage": 42.728}, {"nature": "Relaxed", "evs": {"hp": 188, "atk": 0, "def": 132, "spa": 0, "spd": 188, "spe": 0}, "usage": 36.253}, {"nature": "Sassy", "evs": {"hp": 188, "atk": 0, "def": 164, "spa": 0, "spd": 156, "spe": 0}, "usage": 15.244}, {"nature": "Hardy", "evs": {"hp": 252, "atk": 0, "def": 124, "spa": 0, "spd": 132, "spe": 0}, "usage": 5.775}], "moves": [["Giga Drain", 100.0], ["Spore", 100.0], ["Rage Powder", 100.0], ["Protect", 51.497], ["Sludge Bomb", 42.728]], "teammates": [["Thundurus", 45.214], ["Heatran", 34.294], ["Kangaskhan-Mega", 27.813], ["Landorus-Therian", 22.514], ["Scrafty", 14.28], ["Cresselia", 7.43], ["Azumarill", 6.975], ["Porygon2", 2.809], ["Gardevoir-Mega", 2.729]], "checks": [], "metadata": {"raw": 36.0, "weight": 0.400754100093, "ceiling": 77.0}}, "Kangaskhan-Mega": {"species": "Kangaskhan-Mega", "abilities": [["Parental Bond", 100.0]], "items": [["Kangaskhanite", 100.0]], "spreads": [{"nature": "Adamant", "evs": {"hp": 92, "atk": 252, "def": 44, "spa": 0, "spd": 52, "spe": 68}, "usage": 61.078}, {"nature": "Jolly", "evs": {"hp": 4, "atk": 252, "def": 0, "spa": 0, "spd": 0, "spe": 252}, "usage": 21.79}, {"nature": "Adamant", "evs": {"hp": 180, "atk": 252, "def": 4, "spa": 0, "spd": 12, "spe": 60}, "usage": 8.255}, {"nature": "Jolly", "evs": {"hp": 0, "atk": 252, "def": 0, "spa": 0, "spd": 4, "spe": 252}, "usage": 7.656}], "moves": [["Fake Out", 100.0], ["Return", 76.989], ["Low Kick", 64.897], ["Ice Punch", 61.078], ["Sucker Punch", 38.922], ["Power-Up Punch", 33.882], ["Double-Edge", 23.011]], "teammates": [["Amoonguss", 39.758], ["Thundurus", 36.337], ["Cresselia", 25.78], ["Heatran", 25.418], ["Azumarill", 14.742], ["Landorus-Therian", 11.158], ["Porygon2", 5.289], ["Rotom-Heat", 4.814], ["Garchomp", 4.335], ["Ferrothorn", 3.907], ["Greninja", 3.584], ["Sylveon", 2.45]], "checks": [], "metadata": {"raw": 29.0, "weight": 0.348023923241, "ceiling": 75.0}}, "Cresselia": {"species": "Cresselia", "abilities": [["Levitate", 100.0]], "items": [["Mental Herb", 62.177], ["Life Orb", 31.276], ["Sitrus Berry", 6.546]], "spreads": [{"nature": "Relaxed", "evs": {"hp": 236, "atk": 0, "def": 204, "spa": 0, "spd": 68, "spe": 0}, "usage": 62.177}, {"nature": "Modest", "evs": {"hp": 0, "atk": 0, "def": 164, "spa": 252, "spd": 92, "spe": 0}, "usage": 31.276}, {"nature": "Bold", "evs": {"hp": 220, "atk": 0, "def": 60, "spa": 0, "spd": 228, "spe": 0}, "usage": 6.37}], "moves": [["Psychic", 99.824], ["Ice Beam", 93.454], ["Helping Hand", 68.547], ["Trick Room", 62.354], ["Moonlight", 31.453], ["Energy Ball", 31.276]], "teammates": [["Landorus-Therian", 28.113], ["Kangaskhan-Mega", 26.244], ["Charizard-Mega-Y", 21.025], ["Thundurus-Therian", 20.236], ["Lucario-Mega", 20.236], ["Togekiss", 17.822], ["Amoonguss", 10.812], ["Thundurus", 7.391], ["Lapras", 4.122], ["Raichu", 3.605]], "checks": [], "metadata": {"raw": 20.0, "weight": 0.495714300639, "ceiling": 75.0}}, "Gardevoir-Mega": {"species": "Gardevoir-Mega", "abilities": [["Pixilate", 100.0]], "items": [["Gardevoirite", 100.0]], "spreads": [{"nature": "Modest", "evs": {"hp": 252, "atk": 0, "def": 36, "spa": 196, "spd": 4, "spe": 20}, "usage": 55.547}, {"nature": "Modest", "evs": {"hp": 252, "atk": 0, "def": 108, "spa": 116, "spd": 4, "spe": 28}, "usage": 33.428}, {"nature": "Timid", "evs": {"hp": 0, "atk": 0, "def": 0, "spa": 252, "spd": 4, "spe": 252}, "usage": 5.902}, {"nature": "Timid", "evs": {"hp": 220, "atk": 0, "def": 36, "spa": 196, "spd": 36, "spe": 20}, "usage": 3.984}], "moves": [["Hyper Voice", 100.0], ["Protect", 94.099], ["Trick Room", 92.958], ["Psychic", 59.531], ["Imprison", 33.428]], "teammates": [["Scrafty", 33.573], ["Heatran", 23.269], ["Crobat", 22.221], ["Rhyperior", 22.221], ["Ludicolo", 20.901], ["Hitmontop", 19.973], ["Hydreigon", 6.571], ["Amoonguss", 4.181], ["Milotic", 3.923], ["Volcarona", 3.923], ["Breloom", 3.538], ["Mamoswine", 2.648]], "checks": [], "metadata": {"raw": 43.0, "weight": 0.218980262342, "ceiling": 77.0}}, "Scrafty": {"species": "Scrafty", "abilities": [["Intimidate", 99.006], ["Moxie", 0.575], ["Shed Skin", 0.419]], "items": [["Assault Vest", 84.745], ["Sitrus Berry", 14.26]], "spreads": [{"nature": "Impish", "evs": {"hp": 252, "atk": 236, "def": 12, "spa": 0, "spd": 4, "spe": 4}, "usage": 84.745}, {"nature": "Adamant", "evs": {"hp": 252, "atk": 220, "def": 4, "spa": 0, "spd": 4, "spe": 28}, "usage": 14.26}], "moves": [["Drain Punch", 99.581], ["Knock Off", 99.006], ["Fake Out", 99.006], ["Super Fang", 84.745]], "teammates": [["Gardevoir-Mega", 51.221], ["Amoonguss", 33.38], ["Heatran", 33.3], ["Thundurus", 29.959], ["Landorus-Therian", 27.295], ["Latios", 11.127], ["Clefairy", 10.648]], "checks": [], "metadata": {"raw": 15.0, "weight": 0.411455238121, "ceiling": 77.0}}, "Charizard-Mega-Y": {"species": "Charizard-Mega-Y", "abilities": [["Drought", 100.0]], "items": [["Charizardite Y", 100.0]], "spreads": [{"nature": "Timid", "evs": {"hp": 4, "atk": 0, "def": 0, "spa": 252, "spd": 0, "spe": 252}, "usage": 66.419}, {"nature": "Modest", "evs": {"hp": 252, "atk": 0, "def": 140, "spa": 60, "spd": 12, "spe": 44}, "usage": 18.852}, {"nature": "Timid", "evs": {"hp": 0, "atk": 0, "def": 0, "spa": 244, "spd": 12, "spe": 252}, "usage": 13.528}], "moves": [["Heat Wave", 100.0], ["Solar Beam", 98.798], ["Protect", 98.798], ["Blast Burn", 66.419], ["Flamethrower", 18.852]], "teammates": [["Thundurus-Therian", 55.379], ["Lucario-Mega", 55.379], ["Togekiss", 52.965], ["Cresselia", 44.648], ["Landorus-Therian", 27.088], ["Latios", 15.718], ["Clefairy", 15.239], ["Lapras", 11.279], ["Raichu", 10.762], ["Delphox", 1.002], ["Camerupt", 0.634]], "checks": [], "metadata": {"raw": 33.0, "weight": 0.141472222463, "ceiling": 76.0}}, "Hitmontop": {"species": "Hitmontop", "abilities": [["Intimidate", 100.0]], "items": [["Eject Button", 100.0]], "spreads": [{"nature": "Adamant", "evs": {"hp": 244, "atk": 252, "def": 0, "spa": 0, "spd": 0, "spe": 12}, "usage": 83.289}, {"nature": "Adamant", "evs": {"hp": 252, "atk": 132, "def": 44, "spa": 0, "spd": 76, "spe": 4}, "usage": 16.711}], "moves": [["Wide Guard", 100.0], ["Fake Out", 100.0], ["Close Combat", 100.0], ["Helping Hand", 83.289]], "teammates": [["Crobat", 72.082], ["Rhyperior", 72.082], ["Ludicolo", 70.762], ["Gardevoir-Mega", 49.764], ["Heatran", 17.583], ["Lapras", 14.463], ["Raichu", 13.946]], "checks": [], "metadata": {"raw": 5.0, "weight": 0.755829703921, "ceiling": 75.0}}, "Togekiss": {"species": "Togekiss", "abilities": [["Serene Grace", 100.0], ["Super Luck", 0.0], ["Hustle", 0.0]], "items": [["Choice Scarf", 82.057], ["Safety Goggles", 14.705]], "spreads": [{"nature": "Modest", "evs": {"hp": 36, "atk": 0, "def": 0, "spa": 252, "spd": 0, "spe": 220}, "usage": 82.057}, {"nature": "Calm", "evs": {"hp": 236, "atk": 0, "def": 188, "spa": 0, "spd": 20, "spe": 60}, "usage": 14.705}], "moves": [["Air Slash", 100.0], ["Aura Sphere", 85.295], ["Heat Wave", 82.057], ["Dazzling Gleam", 82.057], ["Roost", 17.943], ["Thunder Wave", 14.705]], "teammates": [["Thundurus-Therian", 71.017], ["Lucario-Mega", 71.017], ["Charizard-Mega-Y", 65.436], ["Cresselia", 46.759], ["Volcarona", 12.727], ["Milotic", 12.727], ["Breloom", 12.341], ["Hydreigon", 11.391], ["Landorus-Therian", 10.347], ["Shedinja", 2.802], ["Gothitelle", 2.802], ["Banette-Mega", 2.793]], "checks": [], "metadata": {"raw": 26.0, "weight": 0.145340336733, "ceiling": 70.0}}, "Ludicolo": {"species": "Ludicolo", "abilities": [["Swift Swim", 89.46], ["Rain Dish", 10.54]], "items": [["Assault Vest", 89.46], ["Damp Rock", 10.54]], "spreads": [{"nature": "Modest", "evs": {"hp": 156, "atk": 0, "def": 52, "spa": 156, "spd": 4, "spe": 140}, "usage": 89.46}, {"nature": "Modest", "evs": {"hp": 252, "atk": 0, "def": 0, "spa": 252, "spd": 4, "spe": 0}, "usage": 10.54}], "moves": [["Scald", 100.0], ["Giga Drain", 100.0], ["Ice Beam", 89.46], ["Fake Out", 89.46], ["Rain Dance", 10.54]], "teammates": [["Crobat", 78.253], ["Rhyperior", 78.253], ["Hitmontop", 76.005], ["Gardevoir-Mega", 55.935], ["Heatran", 23.754], ["Sceptile-Mega", 9.22], ["Noivern", 8.838], ["Greninja", 6.469], ["Politoed", 5.799], ["Ferrothorn", 3.717], ["Breloom", 0.711]], "checks": [], "metadata": {"raw": 14.0, "weight": 0.25131858519, "ceiling": 75.0}}, "Rhyperior": {"species": "Rhyperior", "abilities": [["Solid Rock", 100.0], ["Lightning Rod", 0.0]], "items": [["Weakness Policy", 100.0]], "spreads": [{"nature": "Adamant", "evs": {"hp": 132, "atk": 156, "def": 44, "spa": 0, "spd": 156, "spe": 20}, "usage": 100.0}], "moves": [["Rock Slide", 100.0], ["Protect", 100.0], ["Drill Run", 100.0], ["Earthquake", 100.0]], "teammates": [["Crobat", 88.793], ["Ludicolo", 87.473], ["Hitmontop", 86.545], ["Gardevoir-Mega", 66.475], ["Heatran", 34.294]], "checks": [], "metadata": {"raw": 11.0, "weight": 0.286145673894, "ceiling": 75.0}}, "Crobat": {"species": "Crobat", "abilities": [["Inner Focus", 100.0]], "items": [["Lum Berry", 100.0]], "spreads": [{"nature": "Jolly", "evs": {"hp": 220, "atk": 0, "def": 108, "spa": 0, "spd": 0, "spe": 180}, "usage": 100.0}], "moves": [["Brave Bird", 100.0], ["Tailwind", 100.0], ["Taunt", 100.0], ["Super Fang", 100.0]], "teammates": [["Rhyperior", 88.793], ["Ludicolo", 87.473], ["Hitmontop", 86.545], ["Gardevoir-Mega", 66.475], ["Heatran", 34.294]], "checks": [], "metadata": {"raw": 6.0, "weight": 0.524600402139, "ceiling": 75.0}}, "Lucario-Mega": {"species": "Lucario-Mega", "abilities": [["Adaptability", 100.0]], "items": [["Lucarionite", 100.0]], "spreads": [{"nature": "Timid", "evs": {"hp": 4, "atk": 0, "def": 0, "spa": 252, "spd": 0, "spe": 252}, "usage": 99.999}], "moves": [["Aura Sphere", 100.0], ["Vacuum Wave", 99.999], ["Protect", 99.999], ["Flash Cannon", 99.999]], "teammates": [["Thundurus-Therian", 88.959], ["Togekiss", 86.545], ["Charizard-Mega-Y", 83.377], ["Cresselia", 64.701], ["Landorus-Therian", 28.288]], "checks": [], "metadata": {"raw": 20.0, "weight": 0.155042895182, "ceiling": 70.0}}, "Thundurus-Therian": {"species": "Thundurus-Therian", "abilities": [["Volt Absorb", 100.0]], "items": [["Expert Belt", 100.0]], "spreads": [{"nature": "Timid", "evs": {"hp": 4, "atk": 0, "def": 0, "spa": 252, "spd": 0, "spe": 252}, "usage": 100.0}], "moves": [["Protect", 100.0], ["Thunderbolt", 100.0], ["Hidden Power Ice", 100.0], ["Dark Pulse", 100.0]], "teammates": [["Lucario-Mega", 88.96], ["Togekiss", 86.546], ["Charizard-Mega-Y", 83.378], ["Cresselia", 64.702], ["Landorus-Therian", 28.289]], "checks": [], "metadata": {"raw": 6.0, "weight": 0.516803768275, "ceiling": 70.0}}, "Azumarill": {"species": "Azumarill", "abilities": [["Huge Power", 100.0], ["Thick Fat", 0.0]], "items": [["Sitrus Berry", 100.0]], "spreads": [{"nature": "Adamant", "evs": {"hp": 196, "atk": 252, "def": 20, "spa": 0, "spd": 12, "spe": 28}, "usage": 94.694}, {"nature": "Adamant", "evs": {"hp": 244, "atk": 252, "def": 0, "spa": 0, "spd": 12, "spe": 0}, "usage": 5.306}], "moves": [["Aqua Jet", 100.0], ["Play Rough", 100.0], ["Belly Drum", 100.0], ["Protect", 94.694]], "teammates": [["Kangaskhan-Mega", 64.067], ["Amoonguss", 43.329], ["Thundurus", 39.908], ["Heatran", 28.989], ["Landorus-Therian", 22.984], ["Slaking", 4.867], ["Talonflame", 4.713], ["Raichu", 2.54]], "checks": [], "metadata": {"raw": 10.0, "weight": 0.232243129682, "ceiling": 69.0}}, "Sylveon": {"species": "Sylveon", "abilities": [["Pixilate", 100.0], ["Cute Charm", 0.0]], "items": [["Pixie Plate", 49.366], ["Life Orb", 42.219], ["Choice Specs", 7.129]], "spreads": [{"nature": "Modest", "evs": {"hp": 252, "atk": 0, "def": 140, "spa": 100, "spd": 12, "spe": 0}, "usage": 49.366}, {"nature": "Modest", "evs": {"hp": 188, "atk": 0, "def": 68, "spa": 252, "spd": 0, "spe": 0}, "usage": 42.219}, {"nature": "Modest", "evs": {"hp": 252, "atk": 0, "def": 0, "spa": 252, "spd": 6, "spe": 0}, "usage": 6.244}], "moves": [["Hyper Voice", 100.0], ["Shadow Ball", 97.829], ["Protect", 93.756], ["Calm Mind", 51.537], ["Psyshock", 48.463]], "teammates": [["Scizor", 47.093], ["Weavile", 45.898], ["Zapdos", 45.898], ["Blaziken-Mega", 45.898], ["Porygon2", 39.252], ["Kangaskhan-Mega", 12.529], ["Talonflame", 6.536], ["Slaking", 5.805], ["Raichu", 3.479], ["Gastrodon", 1.195], ["Gengar-Mega", 1.195], ["Quagsire", 0.823]], "checks": [], "metadata": {"raw": 27.0, "weight": 0.0730890174618, "ceiling": 84.0}}, "Aegislash": {"species": "Aegislash", "abilities": [["Stance Change", 100.0]], "items": [["Leftovers", 100.0]], "spreads": [{"nature": "Calm", "evs": {"hp": 252, "atk": 0, "def": 68, "spa": 52, "spd": 132, "spe": 4}, "usage": 55.427}, {"nature": "Quiet", "evs": {"hp": 252, "atk": 0, "def": 0, "spa": 252, "spd": 4, "spe": 0}, "usage": 44.573}], "moves": [["Shadow Ball", 100.0], ["King's Shield", 100.0], ["Wide Guard", 55.427], ["Toxic", 55.427], ["Flash Cannon", 44.573], ["Substitute", 44.573]], "teammates": [["Pinsir-Mega", 52.006], ["Kingdra", 51.571], ["Politoed", 50.686], ["Rotom-Heat", 41.732], ["Garchomp", 41.253], ["Ferrothorn", 40.825], ["Greninja", 40.502], ["Kangaskhan-Mega", 8.64], ["Thundurus", 0.64]], "checks": [], "metadata": {"raw": 25.0, "weight": 0.0693396423817, "ceiling": 80.0}}, "Politoed": {"species": "Politoed", "abilities": [["Drizzle", 100.0], ["Water Absorb", 0.0], ["Damp", 0.0]], "items": [["Life Orb", 72.151], ["Focus Sash", 19.726], ["Leftovers", 8.123]], "spreads": [{"nature": "Modest", "evs": {"hp": 92, "atk": 0, "def": 172, "spa": 244, "spd": 0, "spe": 0}, "usage": 72.151}, {"nature": "Modest", "evs": {"hp": 0, "atk": 0, "def": 0, "spa": 252, "spd": 140, "spe": 116}, "usage": 27.849}], "moves": [["Protect", 100.0], ["Hydro Pump", 100.0], ["Ice Beam", 72.151], ["Helping Hand", 72.151], ["Blizzard", 27.849], ["Earthquake", 27.849]], "teammates": [["Pinsir-Mega", 68.73], ["Kingdra", 68.295], ["Aegislash", 65.979], ["Sceptile-Mega", 26.529], ["Noivern", 26.146], ["Greninja", 23.777], ["Thundurus", 17.365], ["Ferrothorn", 15.977], ["Ludicolo", 15.322], ["Breloom", 5.76]], "checks": [], "metadata": {"raw": 11.0, "weight": 0.121061751275, "ceiling": 80.0}}, "Greninja": {"species": "Greninja", "abilities": [["Protean", 99.997], ["Torrent", 0.003]], "items": [["Life Orb", 99.997]], "spreads": [{"nature": "Hasty", "evs": {"hp": 0, "atk": 4, "def": 0, "spa": 252, "spd": 0, "spe": 252}, "usage": 67.57}, {"nature": "Timid", "evs": {"hp": 0, "atk": 0, "def": 0, "spa": 252, "spd": 4, "spe": 252}, "usage": 32.43}], "moves": [["Dark Pulse", 100.0], ["Ice Beam", 99.997], ["Gunk Shot", 67.567], ["Protect", 67.567], ["Hydro Pump", 32.43], ["U-turn", 32.43]], "teammates": [["Ferrothorn", 86.789], ["Rotom-Heat", 64.726], ["Garchomp", 64.247], ["Aegislash", 61.395], ["Kangaskhan-Mega", 31.633], ["Sceptile-Mega", 31.11], ["Noivern", 30.727], ["Politoed", 27.689], ["Ludicolo", 19.903], ["Breloom", 7.096]], "checks": [], "metadata": {"raw": 45.0, "weight": 0.025412503315, "ceiling": 74.0}}, "Kingdra": {"species": "Kingdra", "abilities": [["Swift Swim", 88.705], ["Sniper", 11.295]], "items": [["Lum Berry", 88.705], ["Scope Lens", 11.295]], "spreads": [{"nature": "Modest", "evs": {"hp": 28, "atk": 0, "def": 28, "spa": 212, "spd": 4, "spe": 236}, "usage": 88.705}, {"nature": "Modest", "evs": {"hp": 4, "atk": 0, "def": 0, "spa": 252, "spd": 0, "spe": 252}, "usage": 11.295}], "moves": [["Rain Dance", 88.705], ["Protect", 88.705], ["Muddy Water", 88.705], ["Draco Meteor", 88.705], ["Scald", 11.295], ["Dragon Pulse", 11.295], ["Ice Beam", 11.295]], "teammates": [["Pinsir-Mega", 85.284], ["Politoed", 83.964], ["Aegislash", 82.533], ["Thundurus", 33.918], ["Landorus-Therian", 16.994], ["Gothitelle", 10.86], ["Shedinja", 10.86], ["Banette-Mega", 10.851], ["Sableye-Mega", 10.381]], "checks": [], "metadata": {"raw": 9.0, "weight": 0.120351890527, "ceiling": 80.0}}, "Ferrothorn": {"species": "Ferrothorn", "abilities": [["Iron Barbs", 100.0]], "items": [["Rocky Helmet", 100.0]], "spreads": [{"nature": "Brave", "evs": {"hp": 252, "atk": 156, "def": 100, "spa": 0, "spd": 0, "spe": 0}, "usage": 73.39}, {"nature": "Relaxed", "evs": {"hp": 252, "atk": 4, "def": 252, "spa": 0, "spd": 0, "spe": 0}, "usage": 16.865}, {"nature": "Bold", "evs": {"hp": 252, "atk": 0, "def": 252, "spa": 4, "spd": 0, "spe": 0}, "usage": 8.085}], "moves": [["Leech Seed", 98.341], ["Protect", 90.256], ["Gyro Ball", 85.508], ["Power Whip", 75.05], ["Spikes", 26.61], ["Thunder", 14.492]], "teammates": [["Greninja", 94.269], ["Rotom-Heat", 70.549], ["Garchomp", 70.07], ["Aegislash", 67.219], ["Kangaskhan-Mega", 37.457], ["Sceptile-Mega", 23.63], ["Noivern", 23.248], ["Politoed", 20.209], ["Ludicolo", 12.423], ["Quagsire", 1.597], ["Umbreon", 1.588], ["Talonflame", 1.066]], "checks": [], "metadata": {"raw": 13.0, "weight": 0.0809862378495, "ceiling": 74.0}}, "Clefairy": {"species": "Clefairy", "abilities": [["Friend Guard", 100.0]], "items": [["Eviolite", 100.0]], "spreads": [{"nature": "Relaxed", "evs": {"hp": 236, "atk": 0, "def": 180, "spa": 0, "spd": 92, "spe": 0}, "usage": 86.74}, {"nature": "Calm", "evs": {"hp": 8, "atk": 0, "def": 244, "spa": 0, "spd": 252, "spe": 0}, "usage": 13.26}], "moves": [["Icy Wind", 100.0], ["Follow Me", 100.0], ["Protect", 86.74], ["Helping Hand", 86.74], ["Moonlight", 13.26]], "teammates": [["Latios", 83.607], ["Charizard-Mega-Y", 70.119], ["Scrafty", 64.767], ["Heatran", 21.035], ["Landorus-Therian", 15.03], ["Snorlax", 12.781], ["Gengar", 12.781], ["Linoone", 12.772], ["Sableye-Mega", 12.345], ["Garchomp", 9.939]], "checks": [], "metadata": {"raw": 6.0, "weight": 0.169109663697, "ceiling": 76.0}}, "Scizor": {"species": "Scizor", "abilities": [["Technician", 100.0], ["Swarm", 0.0]], "items": [["Life Orb", 100.0]], "spreads": [{"nature": "Adamant", "evs": {"hp": 248, "atk": 252, "def": 0, "spa": 0, "spd": 8, "spe": 0}, "usage": 97.462}], "moves": [["Protect", 100.0], ["Bullet Punch", 100.0], ["Bug Bite", 100.0], ["Feint", 97.462]], "teammates": [["Weavile", 93.993], ["Zapdos", 93.993], ["Blaziken-Mega", 93.993], ["Sylveon", 92.974], ["Landorus-Therian", 25.751], ["Gastrodon", 2.448], ["Gengar-Mega", 2.448]], "checks": [], "metadata": {"raw": 12.0, "weight": 0.0832972397513, "ceiling": 84.0}}, "Blaziken-Mega": {"species": "Blaziken-Mega", "abilities": [["Speed Boost", 100.0]], "items": [["Blazikenite", 100.0]], "spreads": [{"nature": "Adamant", "evs": {"hp": 112, "atk": 252, "def": 0, "spa": 0, "spd": 0, "spe": 144}, "usage": 99.996}], "moves": [["Low Kick", 99.996], ["Flare Blitz", 99.996], ["Rock Slide", 99.996], ["Protect", 99.996]], "teammates": [["Zapdos", 96.528], ["Weavile", 96.528], ["Scizor", 96.438], ["Sylveon", 92.97], ["Landorus-Therian", 28.286]], "checks": [], "metadata": {"raw": 23.0, "weight": 0.0423579219775, "ceiling": 84.0}}, "Zapdos": {"species": "Zapdos", "abilities": [["Pressure", 100.0], ["Static", 0.0]], "items": [["Sitrus Berry", 100.0]], "spreads": [{"nature": "Modest", "evs": {"hp": 248, "atk": 0, "def": 0, "spa": 252, "spd": 8, "spe": 0}, "usage": 100.0}], "moves": [["Thunderbolt", 100.0], ["Tailwind", 100.0], ["Hidden Power Grass", 100.0], ["Roost", 100.0]], "teammates": [["Weavile", 96.532], ["Blaziken-Mega", 96.531], ["Scizor", 96.441], ["Sylveon", 92.974], ["Landorus-Therian", 28.289]], "checks": [], "metadata": {"raw": 12.0, "weight": 0.0811830759572, "ceiling": 84.0}}, "Weavile": {"species": "Weavile", "abilities": [["Pickpocket", 100.0], ["Pressure", 0.0]], "items": [["Focus Sash", 100.0]], "spreads": [{"nature": "Jolly", "evs": {"hp": 0, "atk": 252, "def": 0, "spa": 0, "spd": 4, "spe": 252}, "usage": 100.0}], "moves": [["Icicle Crash", 100.0], ["Knock Off", 100.0], ["Low Kick", 100.0], ["Fake Out", 100.0]], "teammates": [["Zapdos", 96.532], ["Blaziken-Mega", 96.531], ["Scizor", 96.441], ["Sylveon", 92.974], ["Landorus-Therian", 28.289]], "checks": [], "metadata": {"raw": 13.0, "weight": 0.0749382239605, "ceiling": 85.0}}, "Pinsir-Mega": {"species": "Pinsir-Mega", "abilities": [["Aerilate", 100.0]], "items": [["Pinsirite", 100.0]], "spreads": [{"nature": "Adamant", "evs": {"hp": 44, "atk": 252, "def": 36, "spa": 0, "spd": 4, "spe": 172}, "usage": 100.0}], "moves": [["Protect", 100.0], ["Return", 100.0], ["Feint", 100.0], ["Close Combat", 100.0]], "teammates": [["Kingdra", 96.144], ["Politoed", 95.259], ["Aegislash", 93.828], ["Thundurus", 45.213], ["Landorus-Therian", 28.289]], "checks": [], "metadata": {"raw": 2.0, "weight": 0.480410742097, "ceiling": 80.0}}, "Garchomp": {"species": "Garchomp", "abilities": [["Rough Skin", 100.0], ["Sand Veil", 0.0]], "items": [["Lum Berry", 82.853], ["Leftovers", 14.427]], "spreads": [{"nature": "Jolly", "evs": {"hp": 0, "atk": 252, "def": 0, "spa": 0, "spd": 4, "spe": 252}, "usage": 100.0}], "moves": [["Earthquake", 97.28], ["Dragon Claw", 85.573], ["Rock Slide", 85.573], ["Protect", 85.573], ["Swords Dance", 17.147], ["Outrage", 14.427]], "teammates": [["Rotom-Heat", 82.732], ["Ferrothorn", 79.105], ["Greninja", 78.782], ["Aegislash", 76.681], ["Kangaskhan-Mega", 46.919], ["Gengar", 13.948], ["Snorlax", 13.948], ["Linoone", 13.939], ["Sableye-Mega", 13.512], ["Clefairy", 10.814], ["Gastrodon", 2.63], ["Gengar-Mega", 2.63]], "checks": [], "metadata": {"raw": 22.0, "weight": 0.0423899547707, "ceiling": 74.0}}, "Hydreigon": {"species": "Hydreigon", "abilities": [["Levitate", 100.0]], "items": [["Choice Specs", 59.7], ["Life Orb", 40.3]], "spreads": [{"nature": "Modest", "evs": {"hp": 0, "atk": 0, "def": 0, "spa": 252, "spd": 4, "spe": 252}, "usage": 59.7}, {"nature": "Timid", "evs": {"hp": 12, "atk": 0, "def": 0, "spa": 244, "spd": 0, "spe": 252}, "usage": 40.3}], "moves": [["Dark Pulse", 100.0], ["Draco Meteor", 100.0], ["Fire Blast", 59.7], ["Earth Power", 59.7], ["Protect", 40.3], ["Tailwind", 40.3]], "teammates": [["Gardevoir-Mega", 66.475], ["Volcarona", 57.721], ["Milotic", 57.721], ["Breloom", 57.336], ["Togekiss", 46.246], ["Gyarados", 38.965], ["Muk", 38.965], ["Mamoswine", 38.965], ["Magnezone", 37.193]], "checks": [], "metadata": {"raw": 17.0, "weight": 0.0547525500008, "ceiling": 68.0}}, "Latios": {"species": "Latios", "abilities": [["Levitate", 100.0]], "items": [["Life Orb", 100.0]], "spreads": [{"nature": "Timid", "evs": {"hp": 0, "atk": 0, "def": 0, "spa": 252, "spd": 4, "spe": 252}, "usage": 100.0}], "moves": [["Protect", 100.0], ["Psychic", 100.0], ["Helping Hand", 100.0], ["Draco Meteor", 100.0]], "teammates": [["Clefairy", 96.387], ["Charizard-Mega-Y", 83.378], ["Scrafty", 78.026], ["Heatran", 34.294], ["Landorus-Therian", 28.289]], "checks": [], "metadata": {"raw": 7.0, "weight": 0.125731216872, "ceiling": 76.0}}, "Magnezone": {"species": "Magnezone", "abilities": [["Analytic", 100.0], ["Sturdy", 0.0]], "items": [["Air Balloon", 56.725], ["Weakness Policy", 42.983]], "spreads": [{"nature": "Modest", "evs": {"hp": 212, "atk": 0, "def": 20, "spa": 252, "spd": 22, "spe": 0}, "usage": 43.73}, {"nature": "Relaxed", "evs": {"hp": 252, "atk": 0, "def": 44, "spa": 60, "spd": 148, "spe": 0}, "usage": 42.983}, {"nature": "Modest", "evs": {"hp": 252, "atk": 0, "def": 0, "spa": 252, "spd": 4, "spe": 0}, "usage": 12.995}], "moves": [["Flash Cannon", 100.0], ["Thunderbolt", 99.708], ["Magnet Rise", 99.708], ["Volt Switch", 57.017], ["Protect", 42.983]], "teammates": [["Hippowdon", 54.963], ["Empoleon", 54.963], ["Tyranitar", 42.371], ["Cradily", 42.371], ["Aerodactyl-Mega", 42.371], ["Gyarados", 41.648], ["Muk", 41.648], ["Mamoswine", 41.648], ["Hydreigon", 39.669], ["Reuniclus", 12.591], ["Steelix", 12.591], ["Tyranitar-Mega", 12.591]], "checks": [], "metadata": {"raw": 10.0, "weight": 0.0872695165576, "ceiling": 63.0}}, "Porygon2": {"species": "Porygon2", "abilities": [["Trace", 100.0]], "items": [["Eviolite", 100.0]], "spreads": [{"nature": "Relaxed", "evs": {"hp": 252, "atk": 0, "def": 92, "spa": 92, "spd": 68, "spe": 0}, "usage": 100.0}], "moves": [["Trick Room", 100.0], ["Sunny Day", 100.0], ["Psyshock", 100.0], ["Ice Beam", 100.0]], "teammates": [["Sylveon", 92.974], ["Kangaskhan-Mega", 64.067], ["Amoonguss", 48.634], ["Thundurus", 45.214], ["Heatran", 34.294]], "checks": [], "metadata": {"raw": 3.0, "weight": 0.27771499309, "ceiling": 65.0}}, "Rotom-Heat": {"species": "Rotom-Heat", "abilities": [["Levitate", 100.0]], "items": [["Charti Berry", 96.821]], "spreads": [{"nature": "Modest", "evs": {"hp": 252, "atk": 0, "def": 0, "spa": 124, "spd": 0, "spe": 132}, "usage": 96.821}], "moves": [["Protect", 100.0], ["Overheat", 100.0], ["Will-O-Wisp", 100.0], ["Thunderbolt", 100.0]], "teammates": [["Garchomp", 96.68], ["Ferrothorn", 93.073], ["Greninja", 92.749], ["Aegislash", 90.649], ["Kangaskhan-Mega", 60.887], ["Gastrodon", 3.089], ["Gengar-Mega", 3.089]], "checks": [], "metadata": {"raw": 6.0, "weight": 0.133006590146, "ceiling": 74.0}}, "Raichu": {"species": "Raichu", "abilities": [["Lightning Rod", 97.171], ["Static", 2.829]], "items": [["Assault Vest", 81.307], ["Eject Button", 15.864]], "spreads": [{"nature": "Timid", "evs": {"hp": 36, "atk": 0, "def": 204, "spa": 20, "spd": 4, "spe": 244}, "usage": 81.307}, {"nature": "Jolly", "evs": {"hp": 252, "atk": 4, "def": 0, "spa": 0, "spd": 0, "spe": 252}, "usage": 15.864}], "moves": [["Volt Switch", 97.171], ["Fake Out", 97.171], ["Nuzzle", 81.307], ["Endeavor", 81.307], ["Protect", 15.864], ["Encore", 15.864]], "teammates": [["Lapras", 79.059], ["Hitmontop", 67.852], ["Charizard-Mega-Y", 64.685], ["Cresselia", 46.009], ["Slaking", 15.425], ["Talonflame", 15.271], ["Landorus-Therian", 9.596], ["Sylveon", 8.838], ["Azumarill", 7.595], ["Excadrill", 2.751], ["Garchomp-Mega", 2.751], ["Krookodile", 2.751]], "checks": [], "metadata": {"raw": 14.0, "weight": 0.055481591309, "ceiling": 70.0}}, "Liepard": {"species": "Liepard", "abilities": [["Prankster", 100.0]], "items": [["Wide Lens", 100.0]], "spreads": [{"nature": "Jolly", "evs": {"hp": 252, "atk": 4, "def": 0, "spa": 0, "spd": 0, "spe": 252}, "usage": 100.0}], "moves": [["Protect", 100.0], ["Foul Play", 100.0], ["Assist", 100.0], ["Swagger", 100.0]], "teammates": [["Smeargle", 97.299], ["Ditto", 97.299], ["Conkeldurr", 97.299]], "checks": [], "metadata": {"raw": 6.0, "weight": 0.126454023729, "ceiling": 61.0}}, "Ditto": {"species": "Ditto", "abilities": [["Imposter", 100.0], ["Limber", 0.0]], "items": [["Leftovers", 100.0]], "spreads": [{"nature": "Bold", "evs": {"hp": 252, "atk": 0, "def": 252, "spa": 0, "spd": 4, "spe": 0}, "usage": 100.0}], "moves": [["Nothing", 300.0], ["Transform", 100.0]], "teammates": [["Smeargle", 97.299], ["Conkeldurr", 97.299], ["Liepard", 97.299]], "checks": [], "metadata": {"raw": 6.0, "weight": 0.126454023729, "ceiling": 61.0}}, "Conkeldurr": {"species": "Conkeldurr", "abilities": [["Iron Fist", 100.0], ["Guts", 0.0]], "items": [["Fist Plate", 100.0]], "spreads": [{"nature": "Adamant", "evs": {"hp": 252, "atk": 252, "def": 4, "spa": 0, "spd": 0, "spe": 0}, "usage": 100.0}], "moves": [["Protect", 100.0], ["Focus Punch", 100.0], ["Counter", 100.0], ["Nothing", 100.0]], "teammates": [["Smeargle", 97.299], ["Ditto", 97.299], ["Liepard", 97.299]], "checks": [], "metadata": {"raw": 6.0, "weight": 0.126454023729, "ceiling": 61.0}}, "Smeargle": {"species": "Smeargle", "abilities": [["Moody", 100.0], ["Technician", 0.0], ["Own Tempo", 0.0]], "items": [["Focus Sash", 100.0]], "spreads": [{"nature": "Adamant", "evs": {"hp": 4, "atk": 252, "def": 0, "spa": 0, "spd": 0, "spe": 252}, "usage": 100.0}], "moves": [["Dark Void", 100.0], ["King's Shield", 100.0], ["Follow Me", 100.0], ["Circle Throw", 100.0]], "teammates": [["Liepard", 97.299], ["Conkeldurr", 97.299], ["Ditto", 97.299]], "checks": [], "metadata": {"raw": 29.0, "weight": 0.0261629014612, "ceiling": 65.0}}, "Breloom": {"species": "Breloom", "abilities": [["Technician", 100.0], ["Effect Spore", 0.0], ["Poison Heal", 0.0]], "items": [["Focus Sash", 100.0]], "spreads": [{"nature": "Jolly", "evs": {"hp": 0, "atk": 252, "def": 0, "spa": 0, "spd": 4, "spe": 252}, "usage": 83.705}, {"nature": "Adamant", "evs": {"hp": 0, "atk": 252, "def": 0, "spa": 0, "spd": 4, "spe": 252}, "usage": 16.295}], "moves": [["Spore", 100.0], ["Bullet Seed", 100.0], ["Protect", 83.705], ["Mach Punch", 83.705], ["Focus Punch", 16.295]], "teammates": [["Milotic", 81.727], ["Volcarona", 81.727], ["Hydreigon", 80.391], ["Togekiss", 70.251], ["Gardevoir-Mega", 50.18], ["Sceptile-Mega", 14.975], ["Noivern", 14.592], ["Greninja", 12.224], ["Politoed", 11.554], ["Ludicolo", 3.768]], "checks": [], "metadata": {"raw": 6.0, "weight": 0.110642708632, "ceiling": 68.0}}, "Lapras": {"species": "Lapras", "abilities": [["Water Absorb", 100.0], ["Shell Armor", 0.0]], "items": [["Leftovers", 100.0]], "spreads": [{"nature": "Quiet", "evs": {"hp": 60, "atk": 0, "def": 60, "spa": 164, "spd": 0, "spe": 0}, "usage": 100.0}], "moves": [["Protect", 100.0], ["Ice Shard", 100.0], ["Hydro Pump", 100.0], ["Freeze-Dry", 100.0]], "teammates": [["Raichu", 97.235], ["Hitmontop", 86.545], ["Charizard-Mega-Y", 83.378], ["Cresselia", 64.702], ["Landorus-Therian", 28.289]], "checks": [], "metadata": {"raw": 7.0, "weight": 0.090220872396, "ceiling": 70.0}}, "Volcarona": {"species": "Volcarona", "abilities": [["Flame Body", 100.0]], "items": [["Lum Berry", 100.0]], "spreads": [{"nature": "Timid", "evs": {"hp": 4, "atk": 0, "def": 0, "spa": 252, "spd": 0, "spe": 252}, "usage": 100.0}], "moves": [["Protect", 100.0], ["Quiver Dance", 100.0], ["Bug Buzz", 100.0], ["Fiery Dance", 100.0]], "teammates": [["Milotic", 98.022], ["Breloom", 97.636], ["Hydreigon", 96.686], ["Togekiss", 86.546], ["Gardevoir-Mega", 66.475]], "checks": [], "metadata": {"raw": 5.0, "weight": 0.111136122973, "ceiling": 68.0}}, "Milotic": {"species": "Milotic", "abilities": [["Competitive", 100.0], ["Marvel Scale", 0.0], ["Cute Charm", 0.0]], "items": [["Leftovers", 100.0]], "spreads": [{"nature": "Bold", "evs": {"hp": 252, "atk": 0, "def": 20, "spa": 0, "spd": 188, "spe": 44}, "usage": 100.0}], "moves": [["Scald", 100.0], ["Mirror Coat", 100.0], ["Recover", 100.0], ["Icy Wind", 100.0]], "teammates": [["Volcarona", 98.022], ["Breloom", 97.636], ["Hydreigon", 96.686], ["Togekiss", 86.546], ["Gardevoir-Mega", 66.475]], "checks": [], "metadata": {"raw": 8.0, "weight": 0.0694600768579, "ceiling": 68.0}}, "Hippowdon": {"species": "Hippowdon", "abilities": [["Sand Stream", 100.0]], "items": [["Nothing", 77.091], ["Smooth Rock", 22.909]], "spreads": [{"nature": "Hardy", "evs": {"hp": 0, "atk": 0, "def": 0, "spa": 0, "spd": 0, "spe": 0}, "usage": 77.091}, {"nature": "Naughty", "evs": {"hp": 252, "atk": 252, "def": 0, "spa": 4, "spd": 0, "spe": 0}, "usage": 22.909}], "moves": [["Earthquake", 77.091], ["Water Pulse", 77.091], ["Stone Edge", 77.091], ["Nothing", 77.091], ["Earth Power", 22.909], ["Stealth Rock", 22.909], ["Toxic", 22.909], ["Fire Fang", 22.909]], "teammates": [["Empoleon", 98.237], ["Magnezone", 96.893], ["Cradily", 75.732], ["Tyranitar", 75.732], ["Aerodactyl-Mega", 75.732], ["Reuniclus", 22.505], ["Steelix", 22.505], ["Tyranitar-Mega", 22.505], ["Tyranitar-Mega", 22.505]], "checks": [], "metadata": {"raw": 6.0, "weight": 0.0825060746228, "ceiling": 57.0}}, "Empoleon": {"species": "Empoleon", "abilities": [["Defiant", 100.0], ["Torrent", 0.0]], "items": [["Assault Vest", 100.0]], "spreads": [{"nature": "Brave", "evs": {"hp": 0, "atk": 248, "def": 228, "spa": 0, "spd": 32, "spe": 0}, "usage": 77.091}, {"nature": "Modest", "evs": {"hp": 252, "atk": 0, "def": 4, "spa": 252, "spd": 0, "spe": 0}, "usage": 22.909}], "moves": [["Drill Peck", 100.0], ["Knock Off", 77.091], ["Steel Wing", 77.091], ["Waterfall", 77.091], ["Scald", 22.909], ["Ice Beam", 22.909], ["Hydro Pump", 22.909]], "teammates": [["Hippowdon", 98.237], ["Magnezone", 96.893], ["Cradily", 75.732], ["Aerodactyl-Mega", 75.732], ["Tyranitar", 75.732], ["Reuniclus", 22.505], ["Steelix", 22.505], ["Tyranitar-Mega", 22.505], ["Tyranitar-Mega", 22.505]], "checks": [], "metadata": {"raw": 6.0, "weight": 0.0825060746228, "ceiling": 57.0}}, "Noivern": {"species": "Noivern", "abilities": [["Infiltrator", 77.548], ["Frisk", 22.452], ["Telepathy", 0.0]], "items": [["White Herb", 77.548], ["Sitrus Berry", 22.452]], "spreads": [{"nature": "Timid", "evs": {"hp": 4, "atk": 0, "def": 0, "spa": 252, "spd": 0, "spe": 252}, "usage": 77.548}, {"nature": "Hardy", "evs": {"hp": 240, "atk": 0, "def": 12, "spa": 0, "spd": 0, "spe": 252}, "usage": 22.452}], "moves": [["Hurricane", 77.548], ["Heat Wave", 77.548], ["Draco Meteor", 77.548], ["U-turn", 77.548], ["Tailwind", 22.452], ["Super Fang", 22.452], ["Taunt", 22.452], ["Protect", 22.452]], "teammates": [["Sceptile-Mega", 76.227], ["Greninja", 73.476], ["Politoed", 72.806], ["Ludicolo", 65.021], ["Ferrothorn", 51.179], ["Blaziken", 22.07], ["Shiftry", 22.07], ["Rotom-Wash", 22.07], ["Aggron", 22.07], ["Breloom", 20.256]], "checks": [], "metadata": {"raw": 18.0, "weight": 0.02656846431, "ceiling": 59.0}}, "Cradily": {"species": "Cradily", "abilities": [["Suction Cups", 100.0], ["Storm Drain", 0.0]], "items": [["Big Root", 100.0]], "spreads": [{"nature": "Gentle", "evs": {"hp": 252, "atk": 4, "def": 0, "spa": 0, "spd": 252, "spe": 0}, "usage": 100.0}], "moves": [["Ingrain", 100.0], ["Giga Drain", 100.0], ["Rock Slide", 100.0], ["Toxic", 100.0]], "teammates": [["Aerodactyl-Mega", 98.641], ["Tyranitar", 98.641], ["Empoleon", 98.237], ["Hippowdon", 98.237], ["Magnezone", 96.893], ["Magnezone", 96.893]], "checks": [], "metadata": {"raw": 5.0, "weight": 0.0763258165683, "ceiling": 57.0}}, "Aerodactyl-Mega": {"species": "Aerodactyl-Mega", "abilities": [["Tough Claws", 100.0]], "items": [["Aerodactylite", 100.0]], "spreads": [{"nature": "Jolly", "evs": {"hp": 0, "atk": 252, "def": 0, "spa": 0, "spd": 4, "spe": 252}, "usage": 100.0}], "moves": [["Hone Claws", 100.0], ["Aerial Ace", 100.0], ["Earthquake", 100.0], ["Stone Edge", 100.0]], "teammates": [["Cradily", 98.641], ["Tyranitar", 98.641], ["Hippowdon", 98.237], ["Empoleon", 98.237], ["Magnezone", 96.893], ["Magnezone", 96.893]], "checks": [], "metadata": {"raw": 6.0, "weight": 0.0636048471402, "ceiling": 57.0}}, "Tyranitar": {"species": "Tyranitar", "abilities": [["Sand Stream", 100.0]], "items": [["Choice Band", 100.0]], "spreads": [{"nature": "Adamant", "evs": {"hp": 196, "atk": 252, "def": 0, "spa": 0, "spd": 0, "spe": 60}, "usage": 100.0}], "moves": [["Crunch", 100.0], ["Pursuit", 100.0], ["Stealth Rock", 100.0], ["Stone Edge", 100.0]], "teammates": [["Cradily", 98.641], ["Aerodactyl-Mega", 98.641], ["Hippowdon", 98.237], ["Empoleon", 98.237], ["Magnezone", 96.893], ["Magnezone", 96.893]], "checks": [], "metadata": {"raw": 14.0, "weight": 0.0272592202029, "ceiling": 69.0}}, "Muk": {"species": "Muk", "abilities": [["Sticky Hold", 100.0], ["Poison Touch", 0.0], ["Stench", 0.0]], "items": [["Assault Vest", 100.0]], "spreads": [{"nature": "Relaxed", "evs": {"hp": 204, "atk": 120, "def": 172, "spa": 0, "spd": 12, "spe": 0}, "usage": 100.0}], "moves": [["Poison Jab", 100.0], ["Shadow Sneak", 100.0], ["Fire Punch", 100.0], ["Rock Tomb", 100.0]], "teammates": [["Mamoswine", 98.664], ["Gyarados", 98.664], ["Magnezone", 96.893], ["Hydreigon", 96.686], ["Gardevoir-Mega", 66.475]], "checks": [], "metadata": {"raw": 7.0, "weight": 0.053587533593, "ceiling": 63.0}}, "Mamoswine": {"species": "Mamoswine", "abilities": [["Thick Fat", 100.0]], "items": [["Focus Sash", 100.0]], "spreads": [{"nature": "Jolly", "evs": {"hp": 4, "atk": 252, "def": 0, "spa": 0, "spd": 0, "spe": 252}, "usage": 100.0}], "moves": [["Protect", 100.0], ["Ice Shard", 100.0], ["Icicle Spear", 100.0], ["Earthquake", 100.0]], "teammates": [["Gyarados", 98.664], ["Muk", 98.664], ["Magnezone", 96.893], ["Hydreigon", 96.686], ["Gardevoir-Mega", 66.475]], "checks": [], "metadata": {"raw": 2.0, "weight": 0.187556367576, "ceiling": 63.0}}, "Gyarados": {"species": "Gyarados", "abilities": [["Intimidate", 100.0], ["Moxie", 0.0]], "items": [["Sitrus Berry", 100.0]], "spreads": [{"nature": "Jolly", "evs": {"hp": 108, "atk": 4, "def": 36, "spa": 0, "spd": 144, "spe": 212}, "usage": 100.0}], "moves": [["Protect", 100.0], ["Taunt", 100.0], ["Thunder Wave", 100.0], ["Waterfall", 100.0]], "teammates": [["Mamoswine", 98.664], ["Muk", 98.664], ["Magnezone", 96.893], ["Hydreigon", 96.686], ["Gardevoir-Mega", 66.475]], "checks": [], "metadata": {"raw": 5.0, "weight": 0.0750225470302, "ceiling": 63.0}}, "Sceptile-Mega": {"species": "Sceptile-Mega", "abilities": [["Lightning Rod", 100.0]], "items": [["Sceptilite", 100.0]], "spreads": [{"nature": "Hardy", "evs": {"hp": 0, "atk": 0, "def": 0, "spa": 252, "spd": 0, "spe": 252}, "usage": 100.0}], "moves": [["Giga Drain", 100.0], ["Leech Seed", 100.0], ["Protect", 100.0], ["Dragon Pulse", 100.0]], "teammates": [["Noivern", 98.297], ["Greninja", 95.929], ["Politoed", 95.259], ["Ludicolo", 87.473], ["Ferrothorn", 67.083], ["Breloom", 26.805]], "checks": [], "metadata": {"raw": 31.0, "weight": 0.0119631541882, "ceiling": 59.0}}, "Sableye-Mega": {"species": "Sableye-Mega", "abilities": [["Magic Bounce", 100.0]], "items": [["Sablenite", 100.0]], "spreads": [{"nature": "Adamant", "evs": {"hp": 248, "atk": 252, "def": 0, "spa": 0, "spd": 8, "spe": 0}, "usage": 52.373}, {"nature": "Bold", "evs": {"hp": 252, "atk": 0, "def": 196, "spa": 0, "spd": 56, "spe": 0}, "usage": 47.627}], "moves": [["Knock Off", 52.373], ["Psych Up", 52.373], ["Shadow Sneak", 52.373], ["Zen Headbutt", 52.373], ["Dark Pulse", 47.627], ["Calm Mind", 47.627], ["Will-O-Wisp", 47.627], ["Recover", 47.627]], "teammates": [["Snorlax", 51.894], ["Gengar", 51.894], ["Linoone", 51.885], ["Garchomp", 49.053], ["Clefairy", 48.761], ["Gothitelle", 47.191], ["Shedinja", 47.191], ["Banette-Mega", 47.182], ["Kingdra", 43.77], ["Togekiss", 34.173]], "checks": [], "metadata": {"raw": 5.0, "weight": 0.0513769989248, "ceiling": 55.0}}, "Talonflame": {"species": "Talonflame", "abilities": [["Gale Wings", 84.481], ["Flame Body", 15.519]], "items": [["Life Orb", 73.991], ["Expert Belt", 15.519], ["Focus Sash", 10.49]], "spreads": [{"nature": "Jolly", "evs": {"hp": 0, "atk": 252, "def": 0, "spa": 0, "spd": 4, "spe": 252}, "usage": 73.991}, {"nature": "Hardy", "evs": {"hp": 0, "atk": 0, "def": 0, "spa": 0, "spd": 0, "spe": 0}, "usage": 15.519}, {"nature": "Adamant", "evs": {"hp": 128, "atk": 252, "def": 0, "spa": 0, "spd": 0, "spe": 128}, "usage": 10.49}], "moves": [["Brave Bird", 100.0], ["Tailwind", 84.481], ["Flare Blitz", 84.481], ["Quick Guard", 73.991], ["Flame Charge", 15.519], ["Acrobatics", 15.519], ["Steel Wing", 15.519]], "teammates": [["Sylveon", 77.455], ["Slaking", 73.552], ["Raichu", 71.225], ["Azumarill", 65.722], ["Kangaskhan-Mega", 38.057], ["Archeops", 15.427], ["Druddigon", 15.427], ["Accelgor", 15.427], ["Escavalier", 15.427], ["Quagsire", 10.428], ["Umbreon", 10.419], ["Ferrothorn", 6.741]], "checks": [], "metadata": {"raw": 17.0, "weight": 0.0097963117194, "ceiling": 62.0}}, "Linoone": {"species": "Linoone", "abilities": [["Gluttony", 100.0]], "items": [["Salac Berry", 98.143]], "spreads": [{"nature": "Jolly", "evs": {"hp": 4, "atk": 252, "def": 0, "spa": 0, "spd": 0, "spe": 252}, "usage": 98.143}], "moves": [["Nothing", 196.286], ["Belly Drum", 100.0], ["Last Resort", 98.143]], "teammates": [["Snorlax", 97.664], ["Gengar", 97.664], ["Sableye-Mega", 97.228], ["Garchomp", 94.822], ["Clefairy", 94.53], ["Clefairy", 94.53]], "checks": [], "metadata": {"raw": 4.0, "weight": 0.034271361692, "ceiling": 49.0}}, "Snorlax": {"species": "Snorlax", "abilities": [["Immunity", 100.0], ["Thick Fat", 0.0]], "items": [["Focus Sash", 100.0]], "spreads": [{"nature": "Adamant", "evs": {"hp": 252, "atk": 252, "def": 0, "spa": 0, "spd": 4, "spe": 0}, "usage": 100.0}], "moves": [["Self-Destruct", 100.0], ["Belly Drum", 100.0], ["Last Resort", 100.0], ["Nothing", 100.0]], "teammates": [["Gengar", 99.521], ["Linoone", 99.512], ["Sableye-Mega", 99.085], ["Garchomp", 96.68], ["Clefairy", 96.387], ["Clefairy", 96.387]], "checks": [], "metadata": {"raw": 6.0, "weight": 0.0224232440133, "ceiling": 55.0}}, "Gengar": {"species": "Gengar", "abilities": [["Levitate", 100.0]], "items": [["Sitrus Berry", 100.0]], "spreads": [{"nature": "Hasty", "evs": {"hp": 0, "atk": 4, "def": 0, "spa": 252, "spd": 0, "spe": 252}, "usage": 100.0}], "moves": [["Drain Punch", 100.0], ["Clear Smog", 100.0], ["Destiny Bond", 100.0], ["Dazzling Gleam", 100.0]], "teammates": [["Snorlax", 99.521], ["Linoone", 99.512], ["Sableye-Mega", 99.085], ["Garchomp", 96.68], ["Clefairy", 96.387], ["Clefairy", 96.387]], "checks": [], "metadata": {"raw": 6.0, "weight": 0.0224232440133, "ceiling": 56.0}}, "Banette-Mega": {"species": "Banette-Mega", "abilities": [["Prankster", 100.0]], "items": [["Banettite", 100.0]], "spreads": [{"nature": "Adamant", "evs": {"hp": 124, "atk": 252, "def": 132, "spa": 0, "spd": 0, "spe": 0}, "usage": 97.961}], "moves": [["Shadow Sneak", 100.0], ["Phantom Force", 97.961], ["Confuse Ray", 97.961], ["Attract", 97.961]], "teammates": [["Gothitelle", 97.526], ["Shedinja", 97.526], ["Sableye-Mega", 97.047], ["Kingdra", 94.105], ["Togekiss", 84.507], ["Umbreon", 1.967], ["Linoone", 1.55]], "checks": [], "metadata": {"raw": 4.0, "weight": 0.0312228783083, "ceiling": 59.0}}, "Slaking": {"species": "Slaking", "abilities": [["Truant", 100.0]], "items": [["Choice Band", 100.0]], "spreads": [{"nature": "Adamant", "evs": {"hp": 252, "atk": 252, "def": 0, "spa": 0, "spd": 4, "spe": 0}, "usage": 100.0}], "moves": [["Night Slash", 100.0], ["Giga Impact", 100.0], ["Retaliate", 100.0], ["Earthquake", 100.0]], "teammates": [["Talonflame", 99.407], ["Raichu", 97.235], ["Sylveon", 92.974], ["Azumarill", 91.731], ["Kangaskhan-Mega", 64.067]], "checks": [], "metadata": {"raw": 6.0, "weight": 0.0205370402317, "ceiling": 59.0}}, "Gothitelle": {"species": "Gothitelle", "abilities": [["Shadow Tag", 100.0]], "items": [["Leftovers", 100.0]], "spreads": [{"nature": "Calm", "evs": {"hp": 252, "atk": 0, "def": 132, "spa": 0, "spd": 124, "spe": 0}, "usage": 100.0}], "moves": [["Protect", 100.0], ["Tickle", 100.0], ["Thunder Wave", 100.0], ["Psyshock", 100.0]], "teammates": [["Shedinja", 99.564], ["Banette-Mega", 99.555], ["Sableye-Mega", 99.085], ["Kingdra", 96.144], ["Togekiss", 86.546], ["Togekiss", 86.546]], "checks": [], "metadata": {"raw": 3.0, "weight": 0.0407818435149, "ceiling": 52.0}}, "Shedinja": {"species": "Shedinja", "abilities": [["Wonder Guard", 100.0]], "items": [["Focus Sash", 100.0]], "spreads": [{"nature": "Jolly", "evs": {"hp": 0, "atk": 252, "def": 4, "spa": 0, "spd": 0, "spe": 252}, "usage": 100.0}], "moves": [["Protect", 100.0], ["Hone Claws", 100.0], ["Shadow Sneak", 100.0], ["Toxic", 100.0]], "teammates": [["Gothitelle", 99.564], ["Banette-Mega", 99.555], ["Sableye-Mega", 99.085], ["Kingdra", 96.144], ["Togekiss", 86.546], ["Togekiss", 86.546]], "checks": [], "metadata": {"raw": 20.0, "weight": 0.00611727652724, "ceiling": 59.0}}, "Tyranitar-Mega": {"species": "Tyranitar-Mega", "abilities": [["Sand Stream", 100.0]], "items": [["Tyranitarite", 100.0]], "spreads": [{"nature": "Adamant", "evs": {"hp": 236, "atk": 252, "def": 0, "spa": 0, "spd": 20, "spe": 0}, "usage": 100.0}], "moves": [["Fire Punch", 100.0], ["Aerial Ace", 100.0], ["Crunch", 100.0], ["Stone Edge", 100.0]], "teammates": [["Reuniclus", 99.596], ["Steelix", 99.596], ["Hippowdon", 98.237], ["Empoleon", 98.237], ["Magnezone", 96.893], ["Magnezone", 96.893]], "checks": [], "metadata": {"raw": 13.0, "weight": 0.0087236434535, "ceiling": 59.0}}, "Reuniclus": {"species": "Reuniclus", "abilities": [["Magic Guard", 100.0], ["Overcoat", 0.0]], "items": [["Life Orb", 100.0]], "spreads": [{"nature": "Sassy", "evs": {"hp": 252, "atk": 0, "def": 0, "spa": 4, "spd": 252, "spe": 0}, "usage": 100.0}], "moves": [["Trick Room", 100.0], ["Recover", 100.0], ["Psychic", 100.0], ["Focus Blast", 100.0]], "teammates": [["Steelix", 99.596], ["Tyranitar-Mega", 99.596], ["Empoleon", 98.237], ["Hippowdon", 98.237], ["Magnezone", 96.893], ["Magnezone", 96.893]], "checks": [], "metadata": {"raw": 2.0, "weight": 0.0567036824477, "ceiling": 55.0}}, "Steelix": {"species": "Steelix", "abilities": [["Rock Head", 100.0]], "items": [["Leftovers", 100.0]], "spreads": [{"nature": "Adamant", "evs": {"hp": 252, "atk": 220, "def": 28, "spa": 0, "spd": 4, "spe": 0}, "usage": 100.0}], "moves": [["Sleep Talk", 100.0], ["Earthquake", 100.0], ["Rest", 100.0], ["Heavy Slam", 100.0]], "teammates": [["Tyranitar-Mega", 99.596], ["Reuniclus", 99.596], ["Empoleon", 98.237], ["Hippowdon", 98.237], ["Magnezone", 96.893]], "checks": [], "metadata": {"raw": 1.0, "weight": 0.113407364895, "ceiling": 55.0}}, "Blaziken": {"species": "Blaziken", "abilities": [["Speed Boost", 100.0], ["Blaze", 0.0]], "items": [["Focus Sash", 100.0]], "spreads": [{"nature": "Brave", "evs": {"hp": 240, "atk": 252, "def": 0, "spa": 0, "spd": 16, "spe": 0}, "usage": 100.0}], "moves": [["Protect", 100.0], ["Flare Blitz", 100.0], ["Knock Off", 100.0], ["Low Kick", 100.0]], "teammates": [["Rotom-Wash", 99.618], ["Shiftry", 99.618], ["Aggron", 99.618], ["Noivern", 98.297], ["Gardevoir-Mega", 66.475]], "checks": [], "metadata": {"raw": 15.0, "weight": 0.0071583051831, "ceiling": 85.0}}, "Aggron": {"species": "Aggron", "abilities": [["Sturdy", 100.0], ["Heavy Metal", 0.0]], "items": [["Choice Band", 100.0]], "spreads": [{"nature": "Adamant", "evs": {"hp": 240, "atk": 252, "def": 12, "spa": 0, "spd": 0, "spe": 0}, "usage": 100.0}], "moves": [["Stone Edge", 100.0], ["Nothing", 100.0], ["Earthquake", 100.0], ["Heavy Slam", 100.0]], "teammates": [["Rotom-Wash", 99.618], ["Blaziken", 99.618], ["Shiftry", 99.618], ["Noivern", 98.297], ["Gardevoir-Mega", 66.475]], "checks": [], "metadata": {"raw": 6.0, "weight": 0.0178957629577, "ceiling": 55.0}}, "Rotom-Wash": {"species": "Rotom-Wash", "abilities": [["Levitate", 100.0]], "items": [["Choice Specs", 100.0]], "spreads": [{"nature": "Modest", "evs": {"hp": 244, "atk": 0, "def": 132, "spa": 0, "spd": 132, "spe": 0}, "usage": 100.0}], "moves": [["Hidden Power Dark", 100.0], ["Thunderbolt", 100.0], ["Volt Switch", 100.0], ["Hydro Pump", 100.0]], "teammates": [["Blaziken", 99.618], ["Shiftry", 99.618], ["Aggron", 99.618], ["Noivern", 98.297], ["Gardevoir-Mega", 66.475]], "checks": [], "metadata": {"raw": 19.0, "weight": 0.0056512935656, "ceiling": 65.0}}, "Shiftry": {"species": "Shiftry", "abilities": [["Early Bird", 100.0], ["Chlorophyll", 0.0]], "items": [["Life Orb", 100.0]], "spreads": [{"nature": "Adamant", "evs": {"hp": 236, "atk": 252, "def": 0, "spa": 0, "spd": 4, "spe": 16}, "usage": 100.0}], "moves": [["Protect", 100.0], ["Knock Off", 100.0], ["Fake Out", 100.0], ["Leaf Blade", 100.0]], "teammates": [["Aggron", 99.618], ["Blaziken", 99.618], ["Rotom-Wash", 99.618], ["Noivern", 98.297], ["Gardevoir-Mega", 66.475]], "checks": [], "metadata": {"raw": 7.0, "weight": 0.0153392253924, "ceiling": 56.0}}, "Delphox": {"species": "Delphox", "abilities": [["Blaze", 100.0]], "items": [["Power Herb", 100.0]], "spreads": [{"nature": "Hardy", "evs": {"hp": 0, "atk": 0, "def": 0, "spa": 0, "spd": 0, "spe": 0}, "usage": 100.0}], "moves": [["Shadow Ball", 100.0], ["Psychic", 100.0], ["Solar Beam", 100.0], ["Flamethrower", 100.0]], "teammates": [["Charizard-Mega-Y", 83.378], ["Camerupt", 63.191], ["Scrafty", 41.344], ["Rhyhorn", 36.609], ["Floatzel", 36.609]], "checks": [], "metadata": {"raw": 6.0, "weight": 0.00934935112457, "ceiling": 55.0}}, "Camerupt": {"species": "Camerupt", "abilities": [["Magma Armor", 100.0], ["Solid Rock", 0.0]], "items": [["Focus Sash", 100.0]], "spreads": [{"nature": "Hardy", "evs": {"hp": 0, "atk": 0, "def": 0, "spa": 0, "spd": 0, "spe": 0}, "usage": 100.0}], "moves": [["Protect", 100.0], ["Eruption", 100.0], ["Stone Edge", 100.0], ["Earthquake", 100.0]], "teammates": [["Delphox", 99.8], ["Charizard-Mega-Y", 83.378], ["Scrafty", 78.026]], "checks": [], "metadata": {"raw": 4.0, "weight": 0.00887968089066, "ceiling": 47.0}}, "Archeops": {"species": "Archeops", "abilities": [["Defeatist", 100.0]], "items": [["Focus Sash", 100.0]], "spreads": [{"nature": "Hardy", "evs": {"hp": 0, "atk": 0, "def": 0, "spa": 0, "spd": 0, "spe": 0}, "usage": 100.0}], "moves": [["Defog", 100.0], ["Acrobatics", 100.0], ["Ancient Power", 100.0], ["Head Smash", 100.0]], "teammates": [["Escavalier", 99.908], ["Accelgor", 99.908], ["Druddigon", 99.908], ["Talonflame", 99.407], ["Scrafty", 78.026]], "checks": [], "metadata": {"raw": 2.0, "weight": 0.0129228420237, "ceiling": 43.0}}, "Druddigon": {"species": "Druddigon", "abilities": [["Rough Skin", 100.0]], "items": [["Absorb Bulb", 100.0]], "spreads": [{"nature": "Hardy", "evs": {"hp": 0, "atk": 0, "def": 0, "spa": 0, "spd": 0, "spe": 0}, "usage": 100.0}], "moves": [["Dragon Tail", 100.0], ["Dragon Claw", 100.0], ["Draco Meteor", 100.0], ["Dragon Pulse", 100.0]], "teammates": [["Escavalier", 99.908], ["Archeops", 99.908], ["Accelgor", 99.908], ["Talonflame", 99.407], ["Scrafty", 78.026]], "checks": [], "metadata": {"raw": 2.0, "weight": 0.0129228420237, "ceiling": 43.0}}, "Accelgor": {"species": "Accelgor", "abilities": [["Hydration", 100.0], ["Sticky Hold", 0.0]], "items": [["Choice Band", 100.0]], "spreads": [{"nature": "Hardy", "evs": {"hp": 0, "atk": 0, "def": 0, "spa": 0, "spd": 0, "spe": 0}, "usage": 100.0}], "moves": [["U-turn", 100.0], ["Signal Beam", 100.0], ["Leech Life", 100.0], ["Bug Buzz", 100.0]], "teammates": [["Druddigon", 99.908], ["Archeops", 99.908], ["Escavalier", 99.908], ["Talonflame", 99.407], ["Scrafty", 78.026], ["Scrafty", 78.026]], "checks": [], "metadata": {"raw": 5.0, "weight": 0.00516913680947, "ceiling": 55.0}}, "Escavalier": {"species": "Escavalier", "abilities": [["Swarm", 100.0]], "items": [["Assault Vest", 100.0]], "spreads": [{"nature": "Hardy", "evs": {"hp": 0, "atk": 0, "def": 0, "spa": 0, "spd": 0, "spe": 0}, "usage": 100.0}], "moves": [["Iron Defense", 100.0], ["Megahorn", 100.0], ["Iron Head", 100.0], ["Bug Buzz", 100.0]], "teammates": [["Archeops", 99.908], ["Accelgor", 99.908], ["Druddigon", 99.908], ["Talonflame", 99.407], ["Scrafty", 78.026], ["Scrafty", 78.026]], "checks": [], "metadata": {"raw": 4.0, "weight": 0.00646142101184, "ceiling": 55.0}}, "Gengar-Mega": {"species": "Gengar-Mega", "abilities": [["Shadow Tag", 100.0]], "items": [["Gengarite", 100.0]], "spreads": [{"nature": "Timid", "evs": {"hp": 0, "atk": 0, "def": 0, "spa": 252, "spd": 4, "spe": 252}, "usage": 100.0}], "moves": [["Sludge Bomb", 100.0], ["Shadow Ball", 100.0], ["Protect", 100.0], ["Perish Song", 100.0]], "teammates": [["Gastrodon", 99.91], ["Rotom-Heat", 97.159], ["Garchomp", 96.68], ["Scizor", 96.441], ["Sylveon", 92.974], ["Sylveon", 92.974]], "checks": [], "metadata": {"raw": 22.0, "weight": 0.00115318025134, "ceiling": 62.0}}, "Gastrodon": {"species": "Gastrodon", "abilities": [["Storm Drain", 100.0]], "items": [["Rocky Helmet", 100.0]], "spreads": [{"nature": "Bold", "evs": {"hp": 252, "atk": 0, "def": 252, "spa": 4, "spd": 0, "spe": 0}, "usage": 100.0}], "moves": [["Protect", 100.0], ["Earth Power", 100.0], ["Scald", 100.0], ["Ice Beam", 100.0]], "teammates": [["Gengar-Mega", 99.91], ["Rotom-Heat", 97.159], ["Garchomp", 96.68], ["Scizor", 96.441], ["Sylveon", 92.974], ["Sylveon", 92.974]], "checks": [], "metadata": {"raw": 5.0, "weight": 0.00507399310591, "ceiling": 85.0}}, "Krookodile": {"species": "Krookodile", "abilities": [["Intimidate", 100.0], ["Moxie", 0.0]], "items": [["Lum Berry", 100.0]], "spreads": [{"nature": "Hardy", "evs": {"hp": 0, "atk": 0, "def": 0, "spa": 0, "spd": 0, "spe": 0}, "usage": 100.0}], "moves": [["Crunch", 100.0], ["Earth Power", 100.0], ["Dark Pulse", 100.0], ["Earthquake", 100.0]], "teammates": [["Excadrill", 99.922], ["Garchomp-Mega", 99.922], ["Simisage", 99.922], ["Raichu", 97.235], ["Garbodor", 66.128], ["Heracross-Mega", 33.794], ["Heracross-Mega", 33.794]], "checks": [], "metadata": {"raw": 9.0, "weight": 0.00244154779589, "ceiling": 62.0}}, "Garchomp-Mega": {"species": "Garchomp-Mega", "abilities": [["Sand Force", 100.0]], "items": [["Garchompite", 100.0]], "spreads": [{"nature": "Hardy", "evs": {"hp": 252, "atk": 252, "def": 4, "spa": 0, "spd": 0, "spe": 0}, "usage": 66.179}, {"nature": "Hardy", "evs": {"hp": 0, "atk": 0, "def": 0, "spa": 0, "spd": 0, "spe": 0}, "usage": 33.821}], "moves": [["Earth Power", 100.0], ["Dragon Pulse", 100.0], ["Dragon Claw", 100.0], ["Earthquake", 100.0]], "teammates": [["Excadrill", 99.922], ["Simisage", 99.922], ["Krookodile", 99.922], ["Raichu", 97.235], ["Garbodor", 66.128], ["Heracross-Mega", 33.794], ["Heracross-Mega", 33.794]], "checks": [], "metadata": {"raw": 15.0, "weight": 0.00146492867753, "ceiling": 55.0}}, "Excadrill": {"species": "Excadrill", "abilities": [["Sand Rush", 100.0], ["Sand Force", 0.0]], "items": [["Sitrus Berry", 100.0]], "spreads": [{"nature": "Hardy", "evs": {"hp": 0, "atk": 0, "def": 0, "spa": 0, "spd": 0, "spe": 0}, "usage": 100.0}], "moves": [["Earth Power", 100.0], ["Iron Head", 100.0], ["Drill Run", 100.0], ["Dig", 66.179], ["Hidden Power Steel", 33.821]], "teammates": [["Garchomp-Mega", 99.922], ["Krookodile", 99.922], ["Simisage", 99.922], ["Raichu", 97.235], ["Garbodor", 66.128], ["Heracross-Mega", 33.794], ["Heracross-Mega", 33.794]], "checks": [], "metadata": {"raw": 6.0, "weight": 0.00366232169384, "ceiling": 55.0}}, "Simisage": {"species": "Simisage", "abilities": [["Gluttony", 100.0]], "items": [["Absorb Bulb", 100.0]], "spreads": [{"nature": "Hardy", "evs": {"hp": 0, "atk": 0, "def": 0, "spa": 0, "spd": 0, "spe": 0}, "usage": 100.0}], "moves": [["Energy Ball", 100.0], ["Leaf Storm", 100.0], ["Bullet Seed", 100.0], ["Giga Drain", 100.0]], "teammates": [["Garchomp-Mega", 99.922], ["Krookodile", 99.922], ["Excadrill", 99.922], ["Raichu", 97.235], ["Garbodor", 66.128], ["Heracross-Mega", 33.794]], "checks": [], "metadata": {"raw": 3.0, "weight": 0.00732464338767, "ceiling": 45.0}}, "Floatzel": {"species": "Floatzel", "abilities": [["Water Veil", 100.0]], "items": [["Lum Berry", 100.0]], "spreads": [{"nature": "Hardy", "evs": {"hp": 0, "atk": 0, "def": 0, "spa": 0, "spd": 0, "spe": 0}, "usage": 100.0}], "moves": [["Ice Fang", 100.0], ["Aqua Jet", 100.0], ["Focus Blast", 100.0], ["Pursuit", 100.0]], "teammates": [["Rhyhorn", 99.927], ["Delphox", 99.8], ["Charizard-Mega-Y", 83.378]], "checks": [], "metadata": {"raw": 2.0, "weight": 0.0102886915924, "ceiling": 44.0}}, "Rhyhorn": {"species": "Rhyhorn", "abilities": [["Lightning Rod", 100.0]], "items": [["Rocky Helmet", 100.0]], "spreads": [{"nature": "Hardy", "evs": {"hp": 0, "atk": 0, "def": 0, "spa": 0, "spd": 0, "spe": 0}, "usage": 100.0}], "moves": [["Horn Attack", 100.0], ["Thunderbolt", 100.0], ["Stone Edge", 100.0], ["Earthquake", 100.0]], "teammates": [["Floatzel", 99.927], ["Delphox", 99.8], ["Charizard-Mega-Y", 83.378]], "checks": [], "metadata": {"raw": 3.0, "weight": 0.00685912772826, "ceiling": 47.0}}, "Umbreon": {"species": "Umbreon", "abilities": [["Synchronize", 100.0], ["Inner Focus", 0.0]], "items": [["Leftovers", 100.0]], "spreads": [{"nature": "Calm", "evs": {"hp": 252, "atk": 0, "def": 132, "spa": 0, "spd": 124, "spe": 0}, "usage": 87.28}, {"nature": "Bold", "evs": {"hp": 252, "atk": 0, "def": 124, "spa": 0, "spd": 128, "spe": 0}, "usage": 12.72}], "moves": [["Foul Play", 100.0], ["Moonlight", 100.0], ["Toxic", 100.0], ["Curse", 87.28]], "teammates": [["Quagsire", 87.218], ["Talonflame", 86.687], ["Ferrothorn", 83.531], ["Sylveon", 80.254], ["Cresselia", 51.982], ["Banette-Mega", 12.275], ["Linoone", 12.232], ["Magnezone", 9.613]], "checks": [], "metadata": {"raw": 7.0, "weight": 0.00285933664005, "ceiling": 55.0}}, "Quagsire": {"species": "Quagsire", "abilities": [["Water Absorb", 100.0]], "items": [["Assault Vest", 100.0]], "spreads": [{"nature": "Adamant", "evs": {"hp": 252, "atk": 252, "def": 0, "spa": 0, "spd": 4, "spe": 0}, "usage": 100.0}], "moves": [["Ice Punch", 100.0], ["Waterfall", 100.0], ["Stone Edge", 100.0], ["Earthquake", 100.0]], "teammates": [["Umbreon", 99.929], ["Talonflame", 99.407], ["Ferrothorn", 96.252], ["Sylveon", 92.974], ["Cresselia", 64.702]], "checks": [], "metadata": {"raw": 2.0, "weight": 0.00873468689597, "ceiling": 48.0}}, "Garbodor": {"species": "Garbodor", "abilities": [["Stench", 100.0]], "items": [["Rocky Helmet", 100.0]], "spreads": [{"nature": "Hardy", "evs": {"hp": 0, "atk": 0, "def": 0, "spa": 0, "spd": 0, "spe": 0}, "usage": 100.0}], "moves": [["Sludge Bomb", 100.0], ["Gunk Shot", 100.0], ["Sludge Wave", 100.0], ["Acid Spray", 100.0]], "teammates": [["Krookodile", 99.922], ["Garchomp-Mega", 99.922], ["Simisage", 99.922], ["Excadrill", 99.922], ["Raichu", 97.235]], "checks": [], "metadata": {"raw": 2.0, "weight": 0.00727111283985, "ceiling": 45.0}}, "Heracross-Mega": {"species": "Heracross-Mega", "abilities": [["Skill Link", 100.0]], "items": [["Heracronite", 100.0]], "spreads": [{"nature": "Hardy", "evs": {"hp": 0, "atk": 0, "def": 0, "spa": 0, "spd": 0, "spe": 0}, "usage": 100.0}], "moves": [["Bug Bite", 100.0], ["Brick Break", 100.0], ["Bulk Up", 100.0], ["Megahorn", 100.0]], "teammates": [["Garchomp-Mega", 99.922], ["Krookodile", 99.922], ["Simisage", 99.922], ["Excadrill", 99.922], ["Raichu", 97.235], ["Raichu", 97.235]], "checks": [], "metadata": {"raw": 6.0, "weight": 0.00123861741388, "ceiling": 56.0}}}